{
  "Version": 3,
  "Meta": {
    "Duration": 3.983,
    "Fps": 60.0,
    "Loop": true,
    "AreBeziersRestricted": true,
    "FadeInTime": 0.0,
    "FadeOutTime": 0.0,
    "CurveCount": 118,
    "TotalSegmentCount": 290,
    "TotalPointCount": 988,
    "UserDataCount": 1,
    "TotalUserDataSize": 0
  },
  "Curves": [
    {
      "Target": "Parameter",
      "Id": "EyeTracking_ParamAngleX",
      "FadeInTime": -1.0,
      "FadeOutTime": -1.0,
      "Segments": [
        0,
        -17.3,
        1,
        0.111,
        -17.037,
        0.222,
        -16.879,
        0.333,
        -16.879,
        1,
        1,
        -16.879,
        1.666,
        -22.558,
        2.333,
        -22.558,
        1,
        2.883,
        -22.558,
        3.433,
        -18.693,
        3.983,
        -17.34
      ]
    },
    {
      "Target": "Parameter",
      "Id": "EyeTracking_ParamAngleY",
      "FadeInTime": -1.0,
      "FadeOutTime": -1.0,
      "Segments": [
        0,
        2.873,
        1,
        0.111,
        2.603,
        0.222,
        2.441,
        0.333,
        2.441,
        1,
        1,
        2.441,
        1.666,
        8.274,
        2.333,
        8.274,
        1,
        2.883,
        8.274,
        3.433,
        4.304,
        3.983,
        2.914
      ]
    },
    {
      "Target": "Parameter",
      "Id": "ParamAngleZ",
      "FadeInTime": -1.0,
      "FadeOutTime": -1.0,
      "Segments": [
        0,
        -23.613,
        1,
        0.111,
        -23.294,
        0.222,
        -23.102,
        0.333,
        -23.102,
        1,
        1,
        -23.102,
        1.666,
        -30,
        2.333,
        -30,
        1,
        2.883,
        -30,
        3.433,
        -25.305,
        3.983,
        -23.662
      ]
    },
    {
      "Target": "Parameter",
      "Id": "ParamHairFront",
      "FadeInTime": -1.0,
      "FadeOutTime": -1.0,
      "Segments": [
        0,
        0.24,
        1,
        0.228,
        0.304,
        0.455,
        0.335,
        0.683,
        0.335,
        1,
        1.016,
        0.335,
        1.35,
        0.268,
        1.683,
        0.132,
        1,
        2.016,
        -0.003,
        2.35,
        -0.071,
        2.683,
        -0.071,
        1,
        3.016,
        -0.071,
        3.35,
        -0.003,
        3.683,
        0.132,
        1,
        3.783,
        0.173,
        3.883,
        0.207,
        3.983,
        0.236
      ]
    },
    {
      "Target": "Parameter",
      "Id": "Param3",
      "FadeInTime": -1.0,
      "FadeOutTime": -1.0,
      "Segments": [
        0,
        -8.069,
        1,
        0.228,
        -6.747,
        0.455,
        -4.004,
        0.683,
        0.142,
        1,
        1.016,
        6.209,
        1.35,
        9.214,
        1.683,
        9.214,
        1,
        2.016,
        9.214,
        2.35,
        6.209,
        2.683,
        0.142,
        1,
        3.016,
        -5.925,
        3.35,
        -8.988,
        3.683,
        -8.988,
        1,
        3.783,
        -8.988,
        3.883,
        -8.713,
        3.983,
        -8.163
      ]
    },
    {
      "Target": "Parameter",
      "Id": "ParamHairSide",
      "FadeInTime": -1.0,
      "FadeOutTime": -1.0,
      "Segments": [
        0,
        0.423,
        1,
        0.228,
        0.474,
        0.455,
        0.5,
        0.683,
        0.5,
        1,
        1.016,
        0.5,
        1.35,
        0.445,
        1.683,
        0.335,
        1,
        2.016,
        0.224,
        2.35,
        0.169,
        2.683,
        0.169,
        1,
        3.016,
        0.169,
        3.35,
        0.224,
        3.683,
        0.335,
        1,
        3.783,
        0.368,
        3.883,
        0.396,
        3.983,
        0.419
      ]
    },
    {
      "Target": "Parameter",
      "Id": "Param4",
      "FadeInTime": -1.0,
      "FadeOutTime": -1.0,
      "Segments": [
        0,
        -3.175,
        1,
        0.228,
        -2.296,
        0.455,
        -0.47,
        0.683,
        2.289,
        1,
        1.016,
        6.326,
        1.35,
        8.326,
        1.683,
        8.326,
        1,
        2.016,
        8.326,
        2.35,
        6.326,
        2.683,
        2.289,
        1,
        3.016,
        -1.749,
        3.35,
        -3.787,
        3.683,
        -3.787,
        1,
        3.783,
        -3.787,
        3.883,
        -3.604,
        3.983,
        -3.238
      ]
    },
    {
      "Target": "Parameter",
      "Id": "Param5",
      "FadeInTime": -1.0,
      "FadeOutTime": -1.0,
      "Segments": [
        0,
        1.098,
        1,
        0.306,
        4.501,
        0.611,
        6.355,
        0.917,
        6.355,
        1,
        1.25,
        6.355,
        1.584,
        4.149,
        1.917,
        0.132,
        1,
        2.25,
        -3.884,
        2.584,
        -5.707,
        2.917,
        -5.707,
        1,
        3.25,
        -5.707,
        3.584,
        -3.884,
        3.917,
        0.132,
        1,
        3.939,
        0.4,
        3.961,
        0.66,
        3.983,
        0.911
      ]
    },
    {
      "Target": "Parameter",
      "Id": "Param6",
      "FadeInTime": -1.0,
      "FadeOutTime": -1.0,
      "Segments": [
        0,
        -5.669,
        1,
        0.306,
        -5.388,
        0.611,
        -3.55,
        0.917,
        0.132,
        1,
        1.25,
        4.149,
        1.584,
        6.355,
        1.917,
        6.355,
        1,
        2.25,
        6.355,
        2.584,
        4.149,
        2.917,
        0.132,
        1,
        3.25,
        -3.884,
        3.584,
        -5.707,
        3.917,
        -5.707,
        1,
        3.939,
        -5.707,
        3.961,
        -5.699,
        3.983,
        -5.682
      ]
    },
    {
      "Target": "Parameter",
      "Id": "Param11",
      "FadeInTime": -1.0,
      "FadeOutTime": -1.0,
      "Segments": [
        0,
        11.29,
        1,
        0.667,
        11.29,
        1.333,
        20.29,
        2,
        20.29,
        1,
        2.661,
        20.29,
        3.322,
        11.439,
        3.983,
        11.291
      ]
    },
    {
      "Target": "Parameter",
      "Id": "Param8",
      "FadeInTime": -1.0,
      "FadeOutTime": -1.0,
      "Segments": [
        0,
        0,
        1,
        0.333,
        4.075,
        0.667,
        6.144,
        1,
        6.144,
        1,
        1.333,
        6.144,
        1.667,
        4.075,
        2,
        0,
        1,
        2.333,
        -4.075,
        2.667,
        -6.08,
        3,
        -6.08,
        1,
        3.328,
        -6.08,
        3.655,
        -4.141,
        3.983,
        -0.202
      ]
    },
    {
      "Target": "Parameter",
      "Id": "Param9",
      "FadeInTime": -1.0,
      "FadeOutTime": -1.0,
      "Segments": [
        0,
        -6.012,
        1,
        0.033,
        -6.057,
        0.067,
        -6.08,
        0.1,
        -6.08,
        1,
        0.433,
        -6.08,
        0.767,
        -4.075,
        1.1,
        0,
        1,
        1.433,
        4.075,
        1.767,
        6.144,
        2.1,
        6.144,
        1,
        2.444,
        6.144,
        2.789,
        4.207,
        3.133,
        0,
        1,
        3.416,
        -3.461,
        3.7,
        -5.536,
        3.983,
        -5.987
      ]
    },
    {
      "Target": "Parameter",
      "Id": "Param10",
      "FadeInTime": -1.0,
      "FadeOutTime": -1.0,
      "Segments": [
        0,
        -0.168,
        1,
        0.067,
        -0.06,
        0.133,
        0,
        0.2,
        0,
        1,
        0.867,
        0,
        1.533,
        -6,
        2.2,
        -6,
        1,
        2.794,
        -6,
        3.389,
        -1.23,
        3.983,
        -0.196
      ]
    },
    {
      "Target": "Parameter",
      "Id": "Param12",
      "FadeInTime": -1.0,
      "FadeOutTime": -1.0,
      "Segments": [
        0,
        0,
        1,
        0.667,
        0,
        1.333,
        -4,
        2,
        -4,
        1,
        2.661,
        -4,
        3.322,
        -0.066,
        3.983,
        -0.001
      ]
    },
    {
      "Target": "Parameter",
      "Id": "Param13",
      "FadeInTime": -1.0,
      "FadeOutTime": -1.0,
      "Segments": [
        0,
        0,
        1,
        0.667,
        0,
        1.333,
        6,
        2,
        6,
        1,
        2.661,
        6,
        3.322,
        0.1,
        3.983,
        0.001
      ]
    },
    {
      "Target": "Parameter",
      "Id": "Param17",
      "FadeInTime": -1.0,
      "FadeOutTime": -1.0,
      "Segments": [
        0,
        0,
        1,
        0.667,
        0,
        1.333,
        3,
        2,
        3,
        1,
        2.661,
        3,
        3.322,
        0.05,
        3.983,
        0.001
      ]
    },
    {
      "Target": "Parameter",
      "Id": "Param14",
      "FadeInTime": -1.0,
      "FadeOutTime": -1.0,
      "Segments": [
        0,
        0,
        1,
        0.333,
        5.031,
        0.667,
        8.411,
        1,
        8.411,
        1,
        1.333,
        8.411,
        1.667,
        5.031,
        2,
        0,
        1,
        2.333,
        -5.031,
        2.667,
        -6.845,
        3,
        -6.845,
        1,
        3.328,
        -6.845,
        3.655,
        -5.091,
        3.983,
        -0.249
      ]
    },
    {
      "Target": "Parameter",
      "Id": "Param15",
      "FadeInTime": -1.0,
      "FadeOutTime": -1.0,
      "Segments": [
        0,
        -5.243,
        1,
        0.033,
        -5.28,
        0.067,
        -5.299,
        0.1,
        -5.299,
        1,
        0.433,
        -5.299,
        0.767,
        -3.66,
        1.1,
        0,
        1,
        1.433,
        3.66,
        1.767,
        5.697,
        2.1,
        5.697,
        1,
        2.444,
        5.697,
        2.789,
        3.787,
        3.133,
        0,
        1,
        3.416,
        -3.116,
        3.7,
        -4.849,
        3.983,
        -5.222
      ]
    },
    {
      "Target": "Parameter",
      "Id": "Param16",
      "FadeInTime": -1.0,
      "FadeOutTime": -1.0,
      "Segments": [
        0,
        0.377,
        1,
        0.078,
        0.136,
        0.155,
        0,
        0.233,
        0,
        1,
        0.9,
        0,
        1.566,
        10,
        2.233,
        10,
        1,
        2.816,
        10,
        3.4,
        2.344,
        3.983,
        0.43
      ]
    },
    {
      "Target": "Parameter",
      "Id": "Param18",
      "FadeInTime": -1.0,
      "FadeOutTime": -1.0,
      "Segments": [
        0,
        0,
        1,
        0.667,
        0,
        1.333,
        -6,
        2,
        -6,
        1,
        2.661,
        -6,
        3.322,
        -0.1,
        3.983,
        -0.001
      ]
    },
    {
      "Target": "Parameter",
      "Id": "Param19",
      "FadeInTime": -1.0,
      "FadeOutTime": -1.0,
      "Segments": [
        0,
        0,
        1,
        0.667,
        0,
        1.333,
        8,
        2,
        8,
        1,
        2.661,
        8,
        3.322,
        0.133,
        3.983,
        0.002
      ]
    },
    {
      "Target": "Parameter",
      "Id": "Param7",
      "FadeInTime": -1.0,
      "FadeOutTime": -1.0,
      "Segments": [
        0,
        6.298,
        1,
        0.356,
        -0.604,
        0.711,
        -8,
        1.067,
        -8,
        1,
        1.734,
        -8,
        2.4,
        18,
        3.067,
        18,
        1,
        3.372,
        18,
        3.678,
        12.538,
        3.983,
        6.621
      ]
    },
    {
      "Target": "Parameter",
      "Id": "Param63",
      "FadeInTime": -1.0,
      "FadeOutTime": -1.0,
      "Segments": [
        0,
        1.452,
        1,
        0.256,
        5.62,
        0.511,
        9,
        0.767,
        9,
        1,
        1.434,
        9,
        2.1,
        -14,
        2.767,
        -14,
        1,
        3.172,
        -14,
        3.578,
        -5.488,
        3.983,
        1.179
      ]
    },
    {
      "Target": "Parameter",
      "Id": "Param91",
      "FadeInTime": -1.0,
      "FadeOutTime": -1.0,
      "Segments": [
        0,
        4.962,
        1,
        0.667,
        4.962,
        1.333,
        0.757,
        2,
        0.757,
        1,
        2.661,
        0.757,
        3.322,
        4.892,
        3.983,
        4.961
      ]
    },
    {
      "Target": "Parameter",
      "Id": "Param81",
      "FadeInTime": -1.0,
      "FadeOutTime": -1.0,
      "Segments": [
        0,
        -2.06,
        1,
        0.1,
        -1.22,
        0.2,
        -0.2,
        0.3,
        1,
        1,
        0.633,
        5,
        0.967,
        7,
        1.3,
        7,
        1,
        1.633,
        7,
        1.967,
        3.888,
        2.3,
        0,
        1,
        2.633,
        -3.888,
        2.967,
        -5,
        3.3,
        -5,
        1,
        3.528,
        -5,
        3.755,
        -4.066,
        3.983,
        -2.198
      ]
    },
    {
      "Target": "Parameter",
      "Id": "Param82",
      "FadeInTime": -1.0,
      "FadeOutTime": -1.0,
      "Segments": [
        0,
        -3.263,
        1,
        0.1,
        -3.297,
        0.2,
        -3.296,
        0.3,
        -3.296,
        1,
        0.633,
        -3.296,
        0.967,
        -2.738,
        1.3,
        -1,
        1,
        1.633,
        0.738,
        1.967,
        2.014,
        2.3,
        2.014,
        1,
        2.633,
        2.014,
        2.967,
        -0.694,
        3.3,
        -2,
        1,
        3.528,
        -2.892,
        3.755,
        -3.17,
        3.983,
        -3.257
      ]
    },
    {
      "Target": "Parameter",
      "Id": "Param83",
      "FadeInTime": -1.0,
      "FadeOutTime": -1.0,
      "Segments": [
        0,
        -8.612,
        1,
        0.1,
        -9.471,
        0.2,
        -10,
        0.3,
        -10,
        1,
        0.633,
        -10,
        0.967,
        -4.436,
        1.3,
        0,
        1,
        1.633,
        4.436,
        1.967,
        5,
        2.3,
        5,
        1,
        2.639,
        5,
        2.978,
        4.458,
        3.317,
        0,
        1,
        3.539,
        -2.924,
        3.761,
        -6.479,
        3.983,
        -8.466
      ]
    },
    {
      "Target": "Parameter",
      "Id": "Param90",
      "FadeInTime": -1.0,
      "FadeOutTime": -1.0,
      "Segments": [
        0,
        2.244,
        1,
        0.1,
        1.419,
        0.2,
        0.354,
        0.3,
        -1,
        1,
        0.633,
        -5.515,
        0.967,
        -9,
        1.3,
        -9,
        1,
        1.633,
        -9,
        1.967,
        -5.416,
        2.3,
        -1,
        1,
        2.639,
        3.489,
        2.978,
        4.764,
        3.317,
        4.764,
        1,
        3.539,
        4.764,
        3.761,
        4.155,
        3.983,
        2.38
      ]
    },
    {
      "Target": "Parameter",
      "Id": "Param84",
      "FadeInTime": -1.0,
      "FadeOutTime": -1.0,
      "Segments": [
        0,
        1,
        1,
        0.333,
        3.387,
        0.667,
        4.212,
        1,
        4.212,
        1,
        1.333,
        4.212,
        1.667,
        2.357,
        2,
        0,
        1,
        2.333,
        -2.357,
        2.667,
        -3.046,
        3,
        -3.046,
        1,
        3.328,
        -3.046,
        3.655,
        -1.442,
        3.983,
        0.881
      ]
    },
    {
      "Target": "Parameter",
      "Id": "Param85",
      "FadeInTime": -1.0,
      "FadeOutTime": -1.0,
      "Segments": [
        0,
        -3.296,
        1,
        0.333,
        -3.296,
        0.667,
        -2.738,
        1,
        -1,
        1,
        1.333,
        0.738,
        1.667,
        2.014,
        2,
        2.014,
        1,
        2.333,
        2.014,
        2.667,
        -0.694,
        3,
        -2,
        1,
        3.328,
        -3.284,
        3.655,
        -3.296,
        3.983,
        -3.296
      ]
    },
    {
      "Target": "Parameter",
      "Id": "Param86",
      "FadeInTime": -1.0,
      "FadeOutTime": -1.0,
      "Segments": [
        0,
        -10.159,
        1,
        0.333,
        -10.159,
        0.667,
        -7.971,
        1,
        -4.82,
        1,
        1.333,
        -1.669,
        1.667,
        -0.578,
        2,
        -0.578,
        1,
        2.339,
        -0.578,
        2.678,
        -1.629,
        3.017,
        -4.82,
        1,
        3.339,
        -7.854,
        3.661,
        -10.082,
        3.983,
        -10.157
      ]
    },
    {
      "Target": "Parameter",
      "Id": "Param87",
      "FadeInTime": -1.0,
      "FadeOutTime": -1.0,
      "Segments": [
        0,
        -5.82,
        1,
        0.333,
        -8.503,
        0.667,
        -9.159,
        1,
        -9.159,
        1,
        1.333,
        -9.159,
        1.667,
        -8.477,
        2,
        -5.82,
        1,
        2.339,
        -3.119,
        2.678,
        -0.814,
        3.017,
        -0.814,
        1,
        3.339,
        -0.814,
        3.661,
        -3.102,
        3.983,
        -5.686
      ]
    },
    {
      "Target": "Parameter",
      "Id": "Param88",
      "FadeInTime": -1.0,
      "FadeOutTime": -1.0,
      "Segments": [
        0,
        -4.416,
        1,
        0.156,
        -3.451,
        0.311,
        -2.01,
        0.467,
        0,
        1,
        0.8,
        4.307,
        1.134,
        7,
        1.467,
        7,
        1,
        1.8,
        7,
        2.134,
        4.307,
        2.467,
        0,
        1,
        2.8,
        -4.307,
        3.134,
        -6,
        3.467,
        -6,
        1,
        3.639,
        -6,
        3.811,
        -5.548,
        3.983,
        -4.517
      ]
    },
    {
      "Target": "Parameter",
      "Id": "Param89",
      "FadeInTime": -1.0,
      "FadeOutTime": -1.0,
      "Segments": [
        0,
        -11.822,
        1,
        0.156,
        -14.405,
        0.311,
        -16,
        0.467,
        -16,
        1,
        0.8,
        -16,
        1.134,
        -9.883,
        1.467,
        -1,
        1,
        1.8,
        7.883,
        2.134,
        11,
        2.467,
        11,
        1,
        2.8,
        11,
        3.134,
        8.676,
        3.467,
        0,
        1,
        3.639,
        -4.483,
        3.811,
        -8.604,
        3.983,
        -11.541
      ]
    },
    {
      "Target": "Parameter",
      "Id": "EyeTracking_ParamBodyAngleX",
      "FadeInTime": -1.0,
      "FadeOutTime": -1.0,
      "Segments": [
        0,
        5.349,
        1,
        0.667,
        5.349,
        1.333,
        1.943,
        2,
        1.943,
        1,
        2.661,
        1.943,
        3.322,
        5.292,
        3.983,
        5.348
      ]
    },
    {
      "Target": "Parameter",
      "Id": "EyeTracking_ParamBodyAngleX2",
      "FadeInTime": -1.0,
      "FadeOutTime": -1.0,
      "Segments": [
        0,
        -10.624,
        1,
        0.667,
        -10.624,
        1.333,
        0.194,
        2,
        0.194,
        1,
        2.661,
        0.194,
        3.322,
        -10.444,
        3.983,
        -10.622
      ]
    },
    {
      "Target": "Parameter",
      "Id": "EyeTracking_ParamBodyAngleY",
      "FadeInTime": -1.0,
      "FadeOutTime": -1.0,
      "Segments": [
        0,
        3.833,
        1,
        0.667,
        3.833,
        1.333,
        0.049,
        2,
        0.049,
        1,
        2.661,
        0.049,
        3.322,
        3.77,
        3.983,
        3.832
      ]
    },
    {
      "Target": "Parameter",
      "Id": "Param60",
      "FadeInTime": -1.0,
      "FadeOutTime": -1.0,
      "Segments": [
        0,
        2.232,
        1,
        0.667,
        2.232,
        1.333,
        -1.896,
        2,
        -1.896,
        1,
        2.661,
        -1.896,
        3.322,
        2.163,
        3.983,
        2.231
      ]
    },
    {
      "Target": "Parameter",
      "Id": "Param62",
      "FadeInTime": -1.0,
      "FadeOutTime": -1.0,
      "Segments": [
        0,
        -7.122,
        1,
        0.667,
        -7.122,
        1.333,
        -11,
        2,
        -11,
        1,
        2.661,
        -11,
        3.322,
        -7.186,
        3.983,
        -7.123
      ]
    },
    {
      "Target": "Parameter",
      "Id": "Param31",
      "FadeInTime": -1.0,
      "FadeOutTime": -1.0,
      "Segments": [
        0,
        -4.791,
        1,
        0.067,
        -4.738,
        0.133,
        -4.708,
        0.2,
        -4.708,
        1,
        0.867,
        -4.708,
        1.533,
        -7.667,
        2.2,
        -7.667,
        1,
        2.794,
        -7.667,
        3.389,
        -5.314,
        3.983,
        -4.805
      ]
    },
    {
      "Target": "Parameter",
      "Id": "Param32",
      "FadeInTime": -1.0,
      "FadeOutTime": -1.0,
      "Segments": [
        0,
        15.385,
        1,
        0.033,
        15.352,
        0.067,
        15.335,
        0.1,
        15.335,
        1,
        0.767,
        15.335,
        1.433,
        22.173,
        2.1,
        22.173,
        1,
        2.728,
        22.173,
        3.355,
        16.11,
        3.983,
        15.402
      ]
    },
    {
      "Target": "Parameter",
      "Id": "ParamBodyAngleZ",
      "FadeInTime": -1.0,
      "FadeOutTime": -1.0,
      "Segments": [
        0,
        5.013,
        1,
        0.667,
        5.013,
        1.333,
        5.819,
        2,
        5.819,
        1,
        2.661,
        5.819,
        3.322,
        5.026,
        3.983,
        5.013
      ]
    },
    {
      "Target": "Parameter",
      "Id": "Param",
      "FadeInTime": -1.0,
      "FadeOutTime": -1.0,
      "Segments": [
        0,
        -4.668,
        1,
        0.006,
        -4.667,
        0.011,
        -4.667,
        0.017,
        -4.667,
        1,
        0.678,
        -4.667,
        1.339,
        -7.87,
        2,
        -7.87,
        1,
        2.661,
        -7.87,
        3.322,
        -4.772,
        3.983,
        -4.67
      ]
    },
    {
      "Target": "Parameter",
      "Id": "Param72",
      "FadeInTime": -1.0,
      "FadeOutTime": -1.0,
      "Segments": [
        0,
        -14.968,
        1,
        0.667,
        -14.968,
        1.333,
        -19.789,
        2,
        -19.789,
        1,
        2.661,
        -19.789,
        3.322,
        -15.048,
        3.983,
        -14.969
      ]
    },
    {
      "Target": "Parameter",
      "Id": "Param50",
      "FadeInTime": -1.0,
      "FadeOutTime": -1.0,
      "Segments": [
        0,
        -15.349,
        1,
        0.667,
        -15.349,
        1.333,
        -3.913,
        2,
        -3.913,
        1,
        2.661,
        -3.913,
        3.322,
        -15.159,
        3.983,
        -15.346
      ]
    },
    {
      "Target": "Parameter",
      "Id": "ParamBreath",
      "FadeInTime": -1.0,
      "FadeOutTime": -1.0,
      "Segments": [
        0,
        1,
        1,
        0.667,
        1,
        1.333,
        0,
        2,
        0,
        1,
        2.456,
        0,
        2.911,
        0.549,
        3.367,
        0.881,
        1,
        3.572,
        0.997,
        3.778,
        1,
        3.983,
        1
      ]
    },
    {
      "Target": "Parameter",
      "Id": "Param21",
      "FadeInTime": -1.0,
      "FadeOutTime": -1.0,
      "Segments": [
        0,
        1.65,
        1,
        0.2,
        2.387,
        0.4,
        2.913,
        0.6,
        2.913,
        1,
        1.267,
        2.913,
        1.933,
        -2.932,
        2.6,
        -2.932,
        1,
        3.061,
        -2.932,
        3.522,
        -0.136,
        3.983,
        1.589
      ]
    },
    {
      "Target": "Parameter",
      "Id": "Param20",
      "FadeInTime": -1.0,
      "FadeOutTime": -1.0,
      "Segments": [
        0,
        -4.577,
        1,
        0.25,
        -2.135,
        0.5,
        -0.181,
        0.75,
        -0.181,
        1,
        1.417,
        -0.181,
        2.083,
        -14.076,
        2.75,
        -14.076,
        1,
        3.161,
        -14.076,
        3.572,
        -8.792,
        3.983,
        -4.741
      ]
    },
    {
      "Target": "Parameter",
      "Id": "Param56",
      "FadeInTime": -1.0,
      "FadeOutTime": -1.0,
      "Segments": [
        0,
        3.482,
        1,
        0.167,
        3.879,
        0.333,
        4.145,
        0.5,
        4.145,
        1,
        1.167,
        4.145,
        1.833,
        -0.1,
        2.5,
        -0.1,
        1,
        2.994,
        -0.1,
        3.489,
        2.235,
        3.983,
        3.441
      ]
    },
    {
      "Target": "Parameter",
      "Id": "Param54",
      "FadeInTime": -1.0,
      "FadeOutTime": -1.0,
      "Segments": [
        0,
        -7.164,
        1,
        0.256,
        -6.384,
        0.511,
        -5.751,
        0.767,
        -5.751,
        1,
        1.434,
        -5.751,
        2.1,
        -10.057,
        2.767,
        -10.057,
        1,
        3.172,
        -10.057,
        3.578,
        -8.463,
        3.983,
        -7.215
      ]
    },
    {
      "Target": "Parameter",
      "Id": "Param55",
      "FadeInTime": -1.0,
      "FadeOutTime": -1.0,
      "Segments": [
        0,
        7.762,
        1,
        0.344,
        3.966,
        0.689,
        0.04,
        1.033,
        0.04,
        1,
        1.7,
        0.04,
        2.366,
        14.749,
        3.033,
        14.749,
        1,
        3.35,
        14.749,
        3.666,
        11.43,
        3.983,
        7.946
      ]
    },
    {
      "Target": "Parameter",
      "Id": "Param22",
      "FadeInTime": -1.0,
      "FadeOutTime": -1.0,
      "Segments": [
        0,
        -13.733,
        1,
        0.111,
        -13.872,
        0.222,
        -13.956,
        0.333,
        -13.956,
        1,
        1,
        -13.956,
        1.666,
        -10.956,
        2.333,
        -10.956,
        1,
        2.883,
        -10.956,
        3.433,
        -12.997,
        3.983,
        -13.712
      ]
    },
    {
      "Target": "Parameter",
      "Id": "Param23",
      "FadeInTime": -1.0,
      "FadeOutTime": -1.0,
      "Segments": [
        0,
        1.687,
        1,
        0.189,
        1.439,
        0.378,
        1.265,
        0.567,
        1.265,
        1,
        1.234,
        1.265,
        1.9,
        3.424,
        2.567,
        3.424,
        1,
        3.039,
        3.424,
        3.511,
        2.341,
        3.983,
        1.709
      ]
    },
    {
      "Target": "Parameter",
      "Id": "Param24",
      "FadeInTime": -1.0,
      "FadeOutTime": -1.0,
      "Segments": [
        0,
        4.397,
        1,
        0.278,
        3.227,
        0.555,
        2.224,
        0.833,
        2.224,
        1,
        1.5,
        2.224,
        2.166,
        8,
        2.833,
        8,
        1,
        3.216,
        8,
        3.6,
        6.09,
        3.983,
        4.467
      ]
    },
    {
      "Target": "Parameter",
      "Id": "EyeTracking_ParamHandLX",
      "FadeInTime": -1.0,
      "FadeOutTime": -1.0,
      "Segments": [
        0,
        15.952,
        1,
        0.122,
        15.45,
        0.245,
        15.143,
        0.367,
        15.143,
        1,
        1.034,
        15.143,
        1.7,
        24.277,
        2.367,
        24.277,
        1,
        2.906,
        24.277,
        3.444,
        18.309,
        3.983,
        16.021
      ]
    },
    {
      "Target": "Parameter",
      "Id": "Param26",
      "FadeInTime": -1.0,
      "FadeOutTime": -1.0,
      "Segments": [
        0,
        -16.581,
        1,
        0.167,
        -16.728,
        0.333,
        -16.826,
        0.5,
        -16.826,
        1,
        1.167,
        -16.826,
        1.833,
        -15.26,
        2.5,
        -15.26,
        1,
        2.994,
        -15.26,
        3.489,
        -16.121,
        3.983,
        -16.566
      ]
    },
    {
      "Target": "Parameter",
      "Id": "Param27",
      "FadeInTime": -1.0,
      "FadeOutTime": -1.0,
      "Segments": [
        0,
        51.101,
        1,
        0.244,
        50.584,
        0.489,
        50.175,
        0.733,
        50.175,
        1,
        1.4,
        50.175,
        2.066,
        53.214,
        2.733,
        53.214,
        1,
        3.15,
        53.214,
        3.566,
        52.027,
        3.983,
        51.137
      ]
    },
    {
      "Target": "Parameter",
      "Id": "Param28",
      "FadeInTime": -1.0,
      "FadeOutTime": -1.0,
      "Segments": [
        0,
        -20.72,
        1,
        0.356,
        -20.016,
        0.711,
        -19.263,
        1.067,
        -19.263,
        1,
        1.734,
        -19.263,
        2.4,
        -21.912,
        3.067,
        -21.912,
        1,
        3.372,
        -21.912,
        3.678,
        -21.356,
        3.983,
        -20.753
      ]
    },
    {
      "Target": "Parameter",
      "Id": "Param65",
      "FadeInTime": -1.0,
      "FadeOutTime": -1.0,
      "Segments": [
        0,
        0,
        1,
        0.667,
        0,
        1.333,
        1.56,
        2,
        1.56,
        1,
        2.661,
        1.56,
        3.322,
        0.026,
        3.983,
        0
      ]
    },
    {
      "Target": "Parameter",
      "Id": "Param66",
      "FadeInTime": -1.0,
      "FadeOutTime": -1.0,
      "Segments": [
        0,
        -2.917,
        1,
        0.667,
        -2.917,
        1.333,
        -4.693,
        2,
        -4.693,
        1,
        2.661,
        -4.693,
        3.322,
        -2.946,
        3.983,
        -2.917
      ]
    },
    {
      "Target": "Parameter",
      "Id": "Param111",
      "FadeInTime": -1.0,
      "FadeOutTime": -1.0,
      "Segments": [
        0,
        13.694,
        1,
        0.111,
        13.698,
        0.222,
        13.7,
        0.333,
        13.7,
        1,
        1,
        13.7,
        1.666,
        13.615,
        2.333,
        13.615,
        1,
        2.883,
        13.615,
        3.433,
        13.672,
        3.983,
        13.692
      ]
    },
    {
      "Target": "Parameter",
      "Id": "Param112",
      "FadeInTime": -1.0,
      "FadeOutTime": -1.0,
      "Segments": [
        0,
        4.03,
        1,
        0.111,
        4.109,
        0.222,
        4.157,
        0.333,
        4.157,
        1,
        1,
        4.157,
        1.666,
        2.44,
        2.333,
        2.44,
        1,
        2.883,
        2.44,
        3.433,
        3.608,
        3.983,
        4.017
      ]
    },
    {
      "Target": "Parameter",
      "Id": "Param93",
      "FadeInTime": -1.0,
      "FadeOutTime": -1.0,
      "Segments": [
        0,
        8.914,
        1,
        0.111,
        8.895,
        0.222,
        8.883,
        0.333,
        8.883,
        1,
        1,
        8.883,
        1.666,
        9.304,
        2.333,
        9.304,
        1,
        2.883,
        9.304,
        3.433,
        9.017,
        3.983,
        8.917
      ]
    },
    {
      "Target": "Parameter",
      "Id": "Param38",
      "FadeInTime": -1.0,
      "FadeOutTime": -1.0,
      "Segments": [
        0,
        -0.222,
        1,
        0.111,
        -0.083,
        0.222,
        0,
        0.333,
        0,
        1,
        1,
        0,
        1.666,
        -3,
        2.333,
        -3,
        1,
        2.883,
        -3,
        3.433,
        -0.958,
        3.983,
        -0.243
      ]
    },
    {
      "Target": "Parameter",
      "Id": "Param94",
      "FadeInTime": -1.0,
      "FadeOutTime": -1.0,
      "Segments": [
        0,
        -2.06,
        1,
        0.111,
        -1.995,
        0.222,
        -1.956,
        0.333,
        -1.956,
        1,
        1,
        -1.956,
        1.666,
        -3.372,
        2.333,
        -3.372,
        1,
        2.883,
        -3.372,
        3.433,
        -2.408,
        3.983,
        -2.071
      ]
    },
    {
      "Target": "Parameter",
      "Id": "EyeTracking_ParamUpLegLX",
      "FadeInTime": -1.0,
      "FadeOutTime": -1.0,
      "Segments": [
        0,
        3.562,
        1,
        0.111,
        3.377,
        0.222,
        3.266,
        0.333,
        3.266,
        1,
        1,
        3.266,
        1.666,
        7.266,
        2.333,
        7.266,
        1,
        2.883,
        7.266,
        3.433,
        4.543,
        3.983,
        3.591
      ]
    },
    {
      "Target": "Parameter",
      "Id": "Param96",
      "FadeInTime": -1.0,
      "FadeOutTime": -1.0,
      "Segments": [
        0,
        -2.543,
        1,
        0.111,
        -2.504,
        0.222,
        -2.481,
        0.333,
        -2.481,
        1,
        1,
        -2.481,
        1.666,
        -3.317,
        2.333,
        -3.317,
        1,
        2.883,
        -3.317,
        3.433,
        -2.748,
        3.983,
        -2.549
      ]
    },
    {
      "Target": "Parameter",
      "Id": "Param97",
      "FadeInTime": -1.0,
      "FadeOutTime": -1.0,
      "Segments": [
        0,
        12.427,
        1,
        0.111,
        12.387,
        0.222,
        12.364,
        0.333,
        12.364,
        1,
        1,
        12.364,
        1.666,
        13.208,
        2.333,
        13.208,
        1,
        2.883,
        13.208,
        3.433,
        12.634,
        3.983,
        12.432
      ]
    },
    {
      "Target": "Parameter",
      "Id": "EyeTracking_ParamLegLX",
      "FadeInTime": -1.0,
      "FadeOutTime": -1.0,
      "Segments": [
        0,
        15.274,
        1,
        0.111,
        15.135,
        0.222,
        15.052,
        0.333,
        15.052,
        1,
        1,
        15.052,
        1.666,
        18.052,
        2.333,
        18.052,
        1,
        2.883,
        18.052,
        3.433,
        16.01,
        3.983,
        15.295
      ]
    },
    {
      "Target": "Parameter",
      "Id": "Param99",
      "FadeInTime": -1.0,
      "FadeOutTime": -1.0,
      "Segments": [
        0,
        1.305,
        1,
        0.111,
        1.342,
        0.222,
        1.364,
        0.333,
        1.364,
        1,
        1,
        1.364,
        1.666,
        0.571,
        2.333,
        0.571,
        1,
        2.883,
        0.571,
        3.433,
        1.111,
        3.983,
        1.3
      ]
    },
    {
      "Target": "Parameter",
      "Id": "Param100",
      "FadeInTime": -1.0,
      "FadeOutTime": -1.0,
      "Segments": [
        0,
        -22.527,
        1,
        0.111,
        -22.571,
        0.222,
        -22.597,
        0.333,
        -22.597,
        1,
        1,
        -22.597,
        1.666,
        -21.658,
        2.333,
        -21.658,
        1,
        2.883,
        -21.658,
        3.433,
        -22.297,
        3.983,
        -22.521
      ]
    },
    {
      "Target": "Parameter",
      "Id": "EyeTracking_ParamFootLX",
      "FadeInTime": -1.0,
      "FadeOutTime": -1.0,
      "Segments": [
        0,
        21.3,
        1,
        0.111,
        21.161,
        0.222,
        21.078,
        0.333,
        21.078,
        1,
        1,
        21.078,
        1.666,
        24.078,
        2.333,
        24.078,
        1,
        2.883,
        24.078,
        3.433,
        22.036,
        3.983,
        21.321
      ]
    },
    {
      "Target": "Parameter",
      "Id": "Param113",
      "FadeInTime": -1.0,
      "FadeOutTime": -1.0,
      "Segments": [
        0,
        30,
        1,
        0.667,
        30,
        1.333,
        29.356,
        2,
        29.356,
        1,
        2.661,
        29.356,
        3.322,
        29.989,
        3.983,
        30
      ]
    },
    {
      "Target": "Parameter",
      "Id": "Param114",
      "FadeInTime": -1.0,
      "FadeOutTime": -1.0,
      "Segments": [
        0,
        11.296,
        1,
        0.667,
        11.296,
        1.333,
        11.868,
        2,
        11.868,
        1,
        2.661,
        11.868,
        3.322,
        11.306,
        3.983,
        11.296
      ]
    },
    {
      "Target": "Parameter",
      "Id": "Param102",
      "FadeInTime": -1.0,
      "FadeOutTime": -1.0,
      "Segments": [
        0,
        1.888,
        1,
        0.667,
        1.888,
        1.333,
        1.787,
        2,
        1.787,
        1,
        2.661,
        1.787,
        3.322,
        1.886,
        3.983,
        1.888
      ]
    },
    {
      "Target": "Parameter",
      "Id": "Param37",
      "FadeInTime": -1.0,
      "FadeOutTime": -1.0,
      "Segments": [
        0,
        0,
        1,
        0.667,
        0,
        1.333,
        10.649,
        2,
        10.649,
        1,
        2.661,
        10.649,
        3.322,
        0.177,
        3.983,
        0.002
      ]
    },
    {
      "Target": "Parameter",
      "Id": "Param103",
      "FadeInTime": -1.0,
      "FadeOutTime": -1.0,
      "Segments": [
        0,
        -5.614,
        1,
        0.667,
        -5.614,
        1.333,
        -7.614,
        2,
        -7.614,
        1,
        2.661,
        -7.614,
        3.322,
        -5.647,
        3.983,
        -5.614
      ]
    },
    {
      "Target": "Parameter",
      "Id": "EyeTracking_ParamUpLegRX",
      "FadeInTime": -1.0,
      "FadeOutTime": -1.0,
      "Segments": [
        0,
        -6.977,
        1,
        0.667,
        -6.977,
        1.333,
        -13.483,
        2,
        -13.483,
        1,
        2.661,
        -13.483,
        3.322,
        -7.085,
        3.983,
        -6.978
      ]
    },
    {
      "Target": "Parameter",
      "Id": "Param105",
      "FadeInTime": -1.0,
      "FadeOutTime": -1.0,
      "Segments": [
        0,
        -8.679,
        1,
        0.667,
        -8.679,
        1.333,
        -8.031,
        2,
        -8.031,
        1,
        2.661,
        -8.031,
        3.322,
        -8.668,
        3.983,
        -8.678
      ]
    },
    {
      "Target": "Parameter",
      "Id": "EyeTracking_ParamLegRX",
      "FadeInTime": -1.0,
      "FadeOutTime": -1.0,
      "Segments": [
        0,
        -10.387,
        1,
        0.667,
        -10.387,
        1.333,
        -15.893,
        2,
        -15.893,
        1,
        2.661,
        -15.893,
        3.322,
        -10.478,
        3.983,
        -10.388
      ]
    },
    {
      "Target": "Parameter",
      "Id": "Param108",
      "FadeInTime": -1.0,
      "FadeOutTime": -1.0,
      "Segments": [
        0,
        0,
        1,
        0.667,
        0,
        1.333,
        -5,
        2,
        -5,
        1,
        2.661,
        -5,
        3.322,
        -0.083,
        3.983,
        -0.001
      ]
    },
    {
      "Target": "Parameter",
      "Id": "Param109",
      "FadeInTime": -1.0,
      "FadeOutTime": -1.0,
      "Segments": [
        0,
        0,
        1,
        0.667,
        0,
        1.333,
        -1,
        2,
        -1,
        1,
        2.661,
        -1,
        3.322,
        -0.017,
        3.983,
        0
      ]
    },
    {
      "Target": "Parameter",
      "Id": "Param110",
      "FadeInTime": -1.0,
      "FadeOutTime": -1.0,
      "Segments": [
        0,
        -13.066,
        1,
        0.667,
        -13.066,
        1.333,
        -19.572,
        2,
        -19.572,
        1,
        2.661,
        -19.572,
        3.322,
        -13.174,
        3.983,
        -13.067
      ]
    },
    {
      "Target": "Parameter",
      "Id": "ParamYureHairFront",
      "FadeInTime": -1.0,
      "FadeOutTime": -1.0,
      "Segments": [
        0,
        0,
        1,
        1.328,
        0,
        2.655,
        0,
        3.983,
        0
      ]
    },
    {
      "Target": "Parameter",
      "Id": "ParamYurePartsA",
      "FadeInTime": -1.0,
      "FadeOutTime": -1.0,
      "Segments": [
        0,
        0,
        1,
        1.328,
        0,
        2.655,
        0,
        3.983,
        0
      ]
    },
    {
      "Target": "Parameter",
      "Id": "ParamYurePartsB",
      "FadeInTime": -1.0,
      "FadeOutTime": -1.0,
      "Segments": [
        0,
        0,
        1,
        1.328,
        0,
        2.655,
        0,
        3.983,
        0
      ]
    },
    {
      "Target": "Parameter",
      "Id": "ParamYureBustX",
      "FadeInTime": -1.0,
      "FadeOutTime": -1.0,
      "Segments": [
        0,
        0,
        1,
        1.328,
        0,
        2.655,
        0,
        3.983,
        0
      ]
    },
    {
      "Target": "Parameter",
      "Id": "ParamYureBustY",
      "FadeInTime": -1.0,
      "FadeOutTime": -1.0,
      "Segments": [
        0,
        0,
        1,
        1.328,
        0,
        2.655,
        0,
        3.983,
        0
      ]
    },
    {
      "Target": "Parameter",
      "Id": "ParamEyeLOpen",
      "FadeInTime": -1.0,
      "FadeOutTime": -1.0,
      "Segments": [
        0,
        1,
        1,
        1.328,
        1,
        2.655,
        1,
        3.983,
        1
      ]
    },
    {
      "Target": "Parameter",
      "Id": "ParamEyeLSmile",
      "FadeInTime": -1.0,
      "FadeOutTime": -1.0,
      "Segments": [
        0,
        0,
        1,
        1.328,
        0,
        2.655,
        0,
        3.983,
        0
      ]
    },
    {
      "Target": "Parameter",
      "Id": "ParamEyeROpen",
      "FadeInTime": -1.0,
      "FadeOutTime": -1.0,
      "Segments": [
        0,
        1,
        1,
        1.328,
        1,
        2.655,
        1,
        3.983,
        1
      ]
    },
    {
      "Target": "Parameter",
      "Id": "ParamEyeRSmile",
      "FadeInTime": -1.0,
      "FadeOutTime": -1.0,
      "Segments": [
        0,
        0,
        1,
        1.328,
        0,
        2.655,
        0,
        3.983,
        0
      ]
    },
    {
      "Target": "Parameter",
      "Id": "EyeTracking_ParamEyeBallX",
      "FadeInTime": -1.0,
      "FadeOutTime": -1.0,
      "Segments": [
        0,
        0.047,
        1,
        1.328,
        0.047,
        2.655,
        0.047,
        3.983,
        0.047
      ]
    },
    {
      "Target": "Parameter",
      "Id": "EyeTracking_ParamEyeBallY",
      "FadeInTime": -1.0,
      "FadeOutTime": -1.0,
      "Segments": [
        0,
        0.055,
        1,
        1.328,
        0.055,
        2.655,
        0.055,
        3.983,
        0.055
      ]
    },
    {
      "Target": "Parameter",
      "Id": "Param70",
      "FadeInTime": -1.0,
      "FadeOutTime": -1.0,
      "Segments": [
        0,
        0,
        1,
        1.328,
        0,
        2.655,
        0,
        3.983,
        0
      ]
    },
    {
      "Target": "Parameter",
      "Id": "ParamBrowLY",
      "FadeInTime": -1.0,
      "FadeOutTime": -1.0,
      "Segments": [
        0,
        0.198,
        1,
        1.328,
        0.198,
        2.655,
        0.198,
        3.983,
        0.198
      ]
    },
    {
      "Target": "Parameter",
      "Id": "ParamBrowRY",
      "FadeInTime": -1.0,
      "FadeOutTime": -1.0,
      "Segments": [
        0,
        0.198,
        1,
        1.328,
        0.198,
        2.655,
        0.198,
        3.983,
        0.198
      ]
    },
    {
      "Target": "Parameter",
      "Id": "ParamBrowLAngle",
      "FadeInTime": -1.0,
      "FadeOutTime": -1.0,
      "Segments": [
        0,
        -0.123,
        1,
        1.328,
        -0.123,
        2.655,
        -0.123,
        3.983,
        -0.123
      ]
    },
    {
      "Target": "Parameter",
      "Id": "ParamBrowRAngle",
      "FadeInTime": -1.0,
      "FadeOutTime": -1.0,
      "Segments": [
        0,
        -0.123,
        1,
        1.328,
        -0.123,
        2.655,
        -0.123,
        3.983,
        -0.123
      ]
    },
    {
      "Target": "Parameter",
      "Id": "ParamBrowLForm",
      "FadeInTime": -1.0,
      "FadeOutTime": -1.0,
      "Segments": [
        0,
        0.348,
        1,
        1.328,
        0.348,
        2.655,
        0.348,
        3.983,
        0.348
      ]
    },
    {
      "Target": "Parameter",
      "Id": "ParamBrowRForm",
      "FadeInTime": -1.0,
      "FadeOutTime": -1.0,
      "Segments": [
        0,
        0.348,
        1,
        1.328,
        0.348,
        2.655,
        0.348,
        3.983,
        0.348
      ]
    },
    {
      "Target": "Parameter",
      "Id": "Param2",
      "FadeInTime": -1.0,
      "FadeOutTime": -1.0,
      "Segments": [
        0,
        0,
        1,
        1.328,
        0,
        2.655,
        0,
        3.983,
        0
      ]
    },
    {
      "Target": "Parameter",
      "Id": "ParamCheek",
      "FadeInTime": -1.0,
      "FadeOutTime": -1.0,
      "Segments": [
        0,
        0,
        1,
        1.328,
        0,
        2.655,
        0,
        3.983,
        0
      ]
    },
    {
      "Target": "Parameter",
      "Id": "ParamMouthForm",
      "FadeInTime": -1.0,
      "FadeOutTime": -1.0,
      "Segments": [
        0,
        0,
        1,
        1.328,
        0,
        2.655,
        0,
        3.983,
        0
      ]
    },
    {
      "Target": "Parameter",
      "Id": "ParamMouthOpenY",
      "FadeInTime": -1.0,
      "FadeOutTime": -1.0,
      "Segments": [
        0,
        0,
        1,
        1.328,
        0,
        2.655,
        0,
        3.983,
        0
      ]
    },
    {
      "Target": "Parameter",
      "Id": "Param92",
      "FadeInTime": -1.0,
      "FadeOutTime": -1.0,
      "Segments": [
        0,
        -2,
        1,
        1.328,
        -2,
        2.655,
        -2,
        3.983,
        -2
      ]
    },
    {
      "Target": "Parameter",
      "Id": "Param71",
      "FadeInTime": -1.0,
      "FadeOutTime": -1.0,
      "Segments": [
        0,
        17.125,
        1,
        1.328,
        17.125,
        2.655,
        17.125,
        3.983,
        17.125
      ]
    },
    {
      "Target": "Parameter",
      "Id": "Param57",
      "FadeInTime": -1.0,
      "FadeOutTime": -1.0,
      "Segments": [
        0,
        0,
        1,
        1.328,
        0,
        2.655,
        0,
        3.983,
        0
      ]
    },
    {
      "Target": "Parameter",
      "Id": "Param58",
      "FadeInTime": -1.0,
      "FadeOutTime": -1.0,
      "Segments": [
        0,
        5,
        1,
        1.328,
        5,
        2.655,
        5,
        3.983,
        5
      ]
    },
    {
      "Target": "Parameter",
      "Id": "Param59",
      "FadeInTime": -1.0,
      "FadeOutTime": -1.0,
      "Segments": [
        0,
        0,
        1,
        1.328,
        0,
        2.655,
        0,
        3.983,
        0
      ]
    },
    {
      "Target": "Parameter",
      "Id": "Param25",
      "FadeInTime": -1.0,
      "FadeOutTime": -1.0,
      "Segments": [
        0,
        7,
        1,
        1.328,
        7,
        2.655,
        7,
        3.983,
        7
      ]
    },
    {
      "Target": "Parameter",
      "Id": "Param64",
      "FadeInTime": -1.0,
      "FadeOutTime": -1.0,
      "Segments": [
        0,
        9.641,
        1,
        1.328,
        9.641,
        2.655,
        9.641,
        3.983,
        9.641
      ]
    },
    {
      "Target": "Parameter",
      "Id": "Param30",
      "FadeInTime": -1.0,
      "FadeOutTime": -1.0,
      "Segments": [
        0,
        0,
        1,
        1.328,
        0,
        2.655,
        0,
        3.983,
        0
      ]
    },
    {
      "Target": "Parameter",
      "Id": "Param29",
      "FadeInTime": -1.0,
      "FadeOutTime": -1.0,
      "Segments": [
        0,
        0,
        1,
        1.328,
        0,
        2.655,
        0,
        3.983,
        0
      ]
    },
    {
      "Target": "Parameter",
      "Id": "Param52",
      "FadeInTime": -1.0,
      "FadeOutTime": -1.0,
      "Segments": [
        0,
        0,
        1,
        1.328,
        0,
        2.655,
        0,
        3.983,
        0
      ]
    },
    {
      "Target": "Parameter",
      "Id": "Param51",
      "FadeInTime": -1.0,
      "FadeOutTime": -1.0,
      "Segments": [
        0,
        0,
        1,
        1.328,
        0,
        2.655,
        0,
        3.983,
        0
      ]
    },
    {
      "Target": "Parameter",
      "Id": "Param53",
      "FadeInTime": -1.0,
      "FadeOutTime": -1.0,
      "Segments": [
        0,
        0,
        1,
        1.328,
        0,
        2.655,
        0,
        3.983,
        0
      ]
    },
    {
      "Target": "Parameter",
      "Id": "Param106",
      "FadeInTime": -1.0,
      "FadeOutTime": -1.0,
      "Segments": [
        0,
        0,
        1,
        1.328,
        0,
        2.655,
        0,
        3.983,
        0
      ]
    }
  ],
  "UserData": [
    {
      "Time": 0.0,
      "Value": ""
    }
  ]
}