{
  "Version": 3,
  "Meta": {
    "Duration": 3.983,
    "Fps": 60.0,
    "Loop": true,
    "AreBeziersRestricted": true,
    "FadeInTime": 0.0,
    "FadeOutTime": 0.0,
    "CurveCount": 225,
    "TotalSegmentCount": 380,
    "TotalPointCount": 1359,
    "UserDataCount": 1,
    "TotalUserDataSize": 0
  },
  "Curves": [
    {
      "Target": "Parameter",
      "Id": "EyeTracking_ParamAngleY",
      "FadeInTime": -1.0,
      "FadeOutTime": -1.0,
      "Segments": [
        0,
        0.004,
        1,
        0.239,
        -3.556,
        0.478,
        -6.331,
        0.717,
        -6.331,
        1,
        1.384,
        -6.331,
        2.05,
        15.278,
        2.717,
        15.278,
        1,
        3.139,
        15.278,
        3.561,
        6.61,
        3.983,
        0.254
      ]
    },
    {
      "Target": "Parameter",
      "Id": "ParamAngleZ",
      "FadeInTime": -1.0,
      "FadeOutTime": -1.0,
      "Segments": [
        0,
        31.996,
        1,
        0.239,
        32.538,
        0.478,
        32.96,
        0.717,
        32.96,
        1,
        1.384,
        32.96,
        2.05,
        29.672,
        2.717,
        29.672,
        1,
        3.139,
        29.672,
        3.561,
        30.991,
        3.983,
        31.958
      ]
    },
    {
      "Target": "Parameter",
      "Id": "Param3",
      "FadeInTime": -1.0,
      "FadeOutTime": -1.0,
      "Segments": [
        0,
        29.375,
        1,
        0.239,
        29.726,
        0.478,
        30,
        0.717,
        30,
        1,
        1.384,
        30,
        2.05,
        27.867,
        2.717,
        27.867,
        1,
        3.139,
        27.867,
        3.561,
        28.723,
        3.983,
        29.35
      ]
    },
    {
      "Target": "Parameter",
      "Id": "ParamHairSideL1",
      "FadeInTime": -1.0,
      "FadeOutTime": -1.0,
      "Segments": [
        0,
        12.752,
        1,
        0.267,
        22.16,
        0.533,
        30,
        0.8,
        30,
        1,
        1.467,
        30,
        2.133,
        -19,
        2.8,
        -19,
        1,
        3.194,
        -19,
        3.589,
        -1.847,
        3.983,
        12.162
      ]
    },
    {
      "Target": "Parameter",
      "Id": "ParamHairSideL2",
      "FadeInTime": -1.0,
      "FadeOutTime": -1.0,
      "Segments": [
        0,
        -27.516,
        1,
        0.6,
        -18.93,
        1.2,
        24,
        1.8,
        24,
        1,
        2.467,
        24,
        3.133,
        -29,
        3.8,
        -29,
        1,
        3.861,
        -29,
        3.922,
        -28.555,
        3.983,
        -27.746
      ]
    },
    {
      "Target": "Parameter",
      "Id": "Param102",
      "FadeInTime": -1.0,
      "FadeOutTime": -1.0,
      "Segments": [
        0,
        -7.395,
        1,
        0.272,
        -18.126,
        0.545,
        -27.194,
        0.817,
        -27.194,
        1,
        1.484,
        -27.194,
        2.15,
        27.194,
        2.817,
        27.194,
        1,
        3.206,
        27.194,
        3.594,
        8.687,
        3.983,
        -6.736
      ]
    },
    {
      "Target": "Parameter",
      "Id": "Param103",
      "FadeInTime": -1.0,
      "FadeOutTime": -1.0,
      "Segments": [
        0,
        24.992,
        1,
        0.606,
        18.822,
        1.211,
        -14.833,
        1.817,
        -14.833,
        1,
        2.484,
        -14.833,
        3.15,
        25.958,
        3.817,
        25.958,
        1,
        3.872,
        25.958,
        3.928,
        25.675,
        3.983,
        25.155
      ]
    },
    {
      "Target": "Parameter",
      "Id": "ParamHairFront1",
      "FadeInTime": -1.0,
      "FadeOutTime": -1.0,
      "Segments": [
        0,
        6.1,
        1,
        0.239,
        13.35,
        0.478,
        19,
        0.717,
        19,
        1,
        1.384,
        19,
        2.05,
        -25,
        2.717,
        -25,
        1,
        3.139,
        -25,
        3.561,
        -7.351,
        3.983,
        5.591
      ]
    },
    {
      "Target": "Parameter",
      "Id": "ParamHairFront2",
      "FadeInTime": -1.0,
      "FadeOutTime": -1.0,
      "Segments": [
        0,
        -15.928,
        1,
        0.572,
        -7.996,
        1.145,
        20,
        1.717,
        20,
        1,
        2.384,
        20,
        3.05,
        -18,
        3.717,
        -18,
        1,
        3.806,
        -18,
        3.894,
        -17.324,
        3.983,
        -16.153
      ]
    },
    {
      "Target": "Parameter",
      "Id": "ParamHairSideR1",
      "FadeInTime": -1.0,
      "FadeOutTime": -1.0,
      "Segments": [
        0,
        8.515,
        1,
        0.183,
        12.353,
        0.367,
        15,
        0.55,
        15,
        1,
        1.217,
        15,
        1.883,
        -20,
        2.55,
        -20,
        1,
        3.028,
        -20,
        3.505,
        -2.024,
        3.983,
        8.163
      ]
    },
    {
      "Target": "Parameter",
      "Id": "ParamHairSideR2",
      "FadeInTime": -1.0,
      "FadeOutTime": -1.0,
      "Segments": [
        0,
        -6.482,
        1,
        0.517,
        2.978,
        1.033,
        24,
        1.55,
        24,
        1,
        2.217,
        24,
        2.883,
        -11,
        3.55,
        -11,
        1,
        3.694,
        -11,
        3.839,
        -9.357,
        3.983,
        -6.783
      ]
    },
    {
      "Target": "Parameter",
      "Id": "Param104",
      "FadeInTime": -1.0,
      "FadeOutTime": -1.0,
      "Segments": [
        0,
        4.704,
        1,
        0.222,
        9.444,
        0.445,
        13,
        0.667,
        13,
        1,
        1.334,
        13,
        2,
        -19,
        2.667,
        -19,
        1,
        3.106,
        -19,
        3.544,
        -5.131,
        3.983,
        4.346
      ]
    },
    {
      "Target": "Parameter",
      "Id": "Param105",
      "FadeInTime": -1.0,
      "FadeOutTime": -1.0,
      "Segments": [
        0,
        -7.037,
        1,
        0.556,
        2.222,
        1.111,
        30,
        1.667,
        30,
        1,
        2.334,
        30,
        3,
        -10,
        3.667,
        -10,
        1,
        3.772,
        -10,
        3.878,
        -8.997,
        3.983,
        -7.309
      ]
    },
    {
      "Target": "Parameter",
      "Id": "Param112",
      "FadeInTime": -1.0,
      "FadeOutTime": -1.0,
      "Segments": [
        0,
        10.593,
        1,
        0.222,
        17.111,
        0.445,
        22,
        0.667,
        22,
        1,
        1.334,
        22,
        2,
        -22,
        2.667,
        -22,
        1,
        3.106,
        -22,
        3.544,
        -2.93,
        3.983,
        10.101
      ]
    },
    {
      "Target": "Parameter",
      "Id": "Param113",
      "FadeInTime": -1.0,
      "FadeOutTime": -1.0,
      "Segments": [
        0,
        -21.037,
        1,
        0.556,
        -11.778,
        1.111,
        16,
        1.667,
        16,
        1,
        2.334,
        16,
        3,
        -24,
        3.667,
        -24,
        1,
        3.772,
        -24,
        3.878,
        -22.997,
        3.983,
        -21.309
      ]
    },
    {
      "Target": "Parameter",
      "Id": "ParamHairBack1",
      "FadeInTime": -1.0,
      "FadeOutTime": -1.0,
      "Segments": [
        0,
        26.118,
        1,
        0.639,
        24.126,
        1.278,
        0.22,
        1.917,
        0.22,
        1,
        2.584,
        0.22,
        3.25,
        26.25,
        3.917,
        26.25,
        1,
        3.939,
        26.25,
        3.961,
        26.221,
        3.983,
        26.165
      ]
    },
    {
      "Target": "Parameter",
      "Id": "ParamHairBack2",
      "FadeInTime": -1.0,
      "FadeOutTime": -1.0,
      "Segments": [
        0,
        14.133,
        1,
        0.306,
        19.817,
        0.611,
        25.063,
        0.917,
        25.063,
        1,
        1.584,
        25.064,
        2.25,
        0.088,
        2.917,
        0.088,
        1,
        3.272,
        0.088,
        3.628,
        7.192,
        3.983,
        13.823
      ]
    },
    {
      "Target": "Parameter",
      "Id": "Param106",
      "FadeInTime": -1.0,
      "FadeOutTime": -1.0,
      "Segments": [
        0,
        25.004,
        1,
        0.078,
        26.279,
        0.155,
        27,
        0.233,
        27,
        1,
        0.9,
        27,
        1.566,
        -26,
        2.233,
        -26,
        1,
        2.816,
        -26,
        3.4,
        14.578,
        3.983,
        24.723
      ]
    },
    {
      "Target": "Parameter",
      "Id": "Param107",
      "FadeInTime": -1.0,
      "FadeOutTime": -1.0,
      "Segments": [
        0,
        -3.919,
        1,
        0.411,
        10.366,
        0.822,
        29,
        1.233,
        29,
        1,
        1.9,
        29,
        2.566,
        -20,
        3.233,
        -20,
        1,
        3.483,
        -20,
        3.733,
        -13.109,
        3.983,
        -4.496
      ]
    },
    {
      "Target": "Parameter",
      "Id": "Param108",
      "FadeInTime": -1.0,
      "FadeOutTime": -1.0,
      "Segments": [
        0,
        24.821,
        1,
        0.022,
        24.939,
        0.045,
        25,
        0.067,
        25,
        1,
        0.734,
        25,
        1.4,
        -30,
        2.067,
        -30,
        1,
        2.706,
        -30,
        3.344,
        20.512,
        3.983,
        24.722
      ]
    },
    {
      "Target": "Parameter",
      "Id": "Param109",
      "FadeInTime": -1.0,
      "FadeOutTime": -1.0,
      "Segments": [
        0,
        -7.496,
        1,
        0.356,
        5.778,
        0.711,
        20,
        1.067,
        20,
        1,
        1.734,
        20,
        2.4,
        -30,
        3.067,
        -30,
        1,
        3.372,
        -30,
        3.678,
        -19.497,
        3.983,
        -8.118
      ]
    },
    {
      "Target": "Parameter",
      "Id": "Param110",
      "FadeInTime": -1.0,
      "FadeOutTime": -1.0,
      "Segments": [
        0,
        21.148,
        1,
        0.111,
        23.556,
        0.222,
        25,
        0.333,
        25,
        1,
        1,
        25,
        1.666,
        -27,
        2.333,
        -27,
        1,
        2.883,
        -27,
        3.433,
        8.393,
        3.983,
        20.78
      ]
    },
    {
      "Target": "Parameter",
      "Id": "Param111",
      "FadeInTime": -1.0,
      "FadeOutTime": -1.0,
      "Segments": [
        0,
        0.681,
        1,
        0.45,
        12.231,
        0.9,
        30,
        1.35,
        30,
        1,
        2.017,
        30,
        2.683,
        -9,
        3.35,
        -9,
        1,
        3.561,
        -9,
        3.772,
        -5.089,
        3.983,
        0.256
      ]
    },
    {
      "Target": "Parameter",
      "Id": "Param101",
      "FadeInTime": -1.0,
      "FadeOutTime": -1.0,
      "Segments": [
        0,
        -1.02,
        1,
        0.35,
        -1.02,
        0.7,
        -0.626,
        1.05,
        0.109,
        1,
        1.367,
        0.774,
        1.683,
        1.08,
        2,
        1.08,
        1,
        2.322,
        1.08,
        2.645,
        0.758,
        2.967,
        0.082,
        1,
        3.306,
        -0.629,
        3.644,
        -1.008,
        3.983,
        -1.02
      ]
    },
    {
      "Target": "Parameter",
      "Id": "EyeTracking_ParamBodyUpperAngleX",
      "FadeInTime": -1.0,
      "FadeOutTime": -1.0,
      "Segments": [
        0,
        -15.515,
        1,
        0.139,
        -18.136,
        0.278,
        -19.791,
        0.417,
        -19.791,
        1,
        1.084,
        -19.791,
        1.75,
        18.343,
        2.417,
        18.343,
        1,
        2.939,
        18.343,
        3.461,
        -5.056,
        3.983,
        -15.196
      ]
    },
    {
      "Target": "Parameter",
      "Id": "EyeTracking_ParamBodyUpperAngleY",
      "FadeInTime": -1.0,
      "FadeOutTime": -1.0,
      "Segments": [
        0,
        4.691,
        1,
        0.067,
        4.555,
        0.133,
        4.48,
        0.2,
        4.48,
        1,
        0.867,
        4.48,
        1.533,
        12,
        2.2,
        12,
        1,
        2.794,
        12,
        3.389,
        6.021,
        3.983,
        4.726
      ]
    },
    {
      "Target": "Parameter",
      "Id": "ParamBodyUpperAngleZ",
      "FadeInTime": -1.0,
      "FadeOutTime": -1.0,
      "Segments": [
        0,
        -26.345,
        1,
        0.033,
        -26.358,
        0.067,
        -26.365,
        0.1,
        -26.365,
        1,
        0.767,
        -26.365,
        1.433,
        -23.544,
        2.1,
        -23.544,
        1,
        2.728,
        -23.544,
        3.355,
        -26.045,
        3.983,
        -26.337
      ]
    },
    {
      "Target": "Parameter",
      "Id": "Param2",
      "FadeInTime": -1.0,
      "FadeOutTime": -1.0,
      "Segments": [
        0,
        8.188,
        1,
        0.033,
        8.21,
        0.067,
        8.222,
        0.1,
        8.222,
        1,
        0.767,
        8.222,
        1.433,
        3.555,
        2.1,
        3.555,
        1,
        2.728,
        3.555,
        3.355,
        7.693,
        3.983,
        8.176
      ]
    },
    {
      "Target": "Parameter",
      "Id": "ParamBodyLowerAngleX",
      "FadeInTime": -1.0,
      "FadeOutTime": -1.0,
      "Segments": [
        0,
        -13,
        1,
        0.667,
        -13,
        1.333,
        30,
        2,
        30,
        1,
        2.661,
        30,
        3.322,
        -12.286,
        3.983,
        -12.991
      ]
    },
    {
      "Target": "Parameter",
      "Id": "ParamBodyLowerAngleZ",
      "FadeInTime": -1.0,
      "FadeOutTime": -1.0,
      "Segments": [
        0,
        -21.829,
        1,
        0.344,
        -21.829,
        0.689,
        -19.059,
        1.033,
        -13.776,
        1,
        1.355,
        -8.833,
        1.678,
        -6.486,
        2,
        -6.486,
        1,
        2.322,
        -6.486,
        2.645,
        -8.833,
        2.967,
        -13.776,
        1,
        3.306,
        -18.974,
        3.644,
        -21.739,
        3.983,
        -21.826
      ]
    },
    {
      "Target": "Parameter",
      "Id": "Param97",
      "FadeInTime": -1.0,
      "FadeOutTime": -1.0,
      "Segments": [
        0,
        22.425,
        1,
        0.072,
        22.317,
        0.145,
        22.256,
        0.217,
        22.256,
        1,
        0.884,
        22.256,
        1.55,
        27.416,
        2.217,
        27.416,
        1,
        2.806,
        27.416,
        3.394,
        23.39,
        3.983,
        22.45
      ]
    },
    {
      "Target": "Parameter",
      "Id": "Param98",
      "FadeInTime": -1.0,
      "FadeOutTime": -1.0,
      "Segments": [
        0,
        -22.368,
        1,
        0.144,
        -22.814,
        0.289,
        -23.098,
        0.433,
        -23.098,
        1,
        1.1,
        -23.098,
        1.766,
        -17.038,
        2.433,
        -17.038,
        1,
        2.95,
        -17.038,
        3.466,
        -20.678,
        3.983,
        -22.316
      ]
    },
    {
      "Target": "Parameter",
      "Id": "ParamBustX",
      "FadeInTime": -1.0,
      "FadeOutTime": -1.0,
      "Segments": [
        0,
        -3.102,
        1,
        0.3,
        -14.287,
        0.6,
        -20,
        0.9,
        -20,
        1,
        1.244,
        -20,
        1.589,
        -12.416,
        1.933,
        2.046,
        1,
        2.255,
        15.575,
        2.578,
        22,
        2.9,
        22,
        1,
        3.228,
        22,
        3.555,
        15.289,
        3.883,
        1.523,
        1,
        3.916,
        0.123,
        3.95,
        -1.21,
        3.983,
        -2.475
      ]
    },
    {
      "Target": "Parameter",
      "Id": "ParamBustY",
      "FadeInTime": -1.0,
      "FadeOutTime": -1.0,
      "Segments": [
        0,
        -17.971,
        1,
        0.117,
        -20.059,
        0.233,
        -21.324,
        0.35,
        -21.324,
        1,
        1.017,
        -21.324,
        1.683,
        19.991,
        2.35,
        19.991,
        1,
        2.894,
        19.991,
        3.439,
        -7.564,
        3.983,
        -17.667
      ]
    },
    {
      "Target": "Parameter",
      "Id": "Param96",
      "FadeInTime": -1.0,
      "FadeOutTime": -1.0,
      "Segments": [
        0,
        5.844,
        1,
        0.394,
        -6.059,
        0.789,
        -20.634,
        1.183,
        -20.634,
        1,
        1.85,
        -20.634,
        2.516,
        21,
        3.183,
        21,
        1,
        3.45,
        21,
        3.716,
        14.339,
        3.983,
        6.345
      ]
    },
    {
      "Target": "Parameter",
      "Id": "ParamBreath",
      "FadeInTime": -1.0,
      "FadeOutTime": -1.0,
      "Segments": [
        0,
        0,
        1,
        0.667,
        0,
        1.333,
        1,
        2,
        1,
        1,
        2.661,
        1,
        3.322,
        0.017,
        3.983,
        0
      ]
    },
    {
      "Target": "Parameter",
      "Id": "ParamArmUpperLZ",
      "FadeInTime": -1.0,
      "FadeOutTime": -1.0,
      "Segments": [
        0,
        58.313,
        1,
        0.167,
        57.243,
        0.333,
        56.53,
        0.5,
        56.53,
        1,
        1.167,
        56.53,
        1.833,
        67.944,
        2.5,
        67.944,
        1,
        2.994,
        67.944,
        3.489,
        61.665,
        3.983,
        58.422
      ]
    },
    {
      "Target": "Parameter",
      "Id": "ParamArmUpperLX",
      "FadeInTime": -1.0,
      "FadeOutTime": -1.0,
      "Segments": [
        0,
        -13.977,
        1,
        0.167,
        -17.837,
        0.333,
        -20.41,
        0.5,
        -20.41,
        1,
        1.167,
        -20.41,
        1.833,
        20.759,
        2.5,
        20.759,
        1,
        2.994,
        20.759,
        3.489,
        -1.887,
        3.983,
        -13.587
      ]
    },
    {
      "Target": "Parameter",
      "Id": "ParamArmUpperLY",
      "FadeInTime": -1.0,
      "FadeOutTime": -1.0,
      "Segments": [
        0,
        -7.222,
        1,
        0.167,
        -7.414,
        0.333,
        -7.541,
        0.5,
        -7.541,
        1,
        1.167,
        -7.541,
        1.833,
        -5.501,
        2.5,
        -5.501,
        1,
        2.994,
        -5.501,
        3.489,
        -6.623,
        3.983,
        -7.203
      ]
    },
    {
      "Target": "Parameter",
      "Id": "ParamArmLowerLZ",
      "FadeInTime": -1.0,
      "FadeOutTime": -1.0,
      "Segments": [
        0,
        5.258,
        1,
        0.267,
        6.03,
        0.533,
        6.673,
        0.8,
        6.673,
        1,
        1.467,
        6.673,
        2.133,
        2.652,
        2.8,
        2.652,
        1,
        3.194,
        2.652,
        3.589,
        4.06,
        3.983,
        5.209
      ]
    },
    {
      "Target": "Parameter",
      "Id": "ParamArmLowerLX",
      "FadeInTime": -1.0,
      "FadeOutTime": -1.0,
      "Segments": [
        0,
        -5.704,
        1,
        0.267,
        -13.617,
        0.533,
        -20.211,
        0.8,
        -20.211,
        1,
        1.467,
        -20.211,
        2.133,
        21.003,
        2.8,
        21.003,
        1,
        3.194,
        21.003,
        3.589,
        6.576,
        3.983,
        -5.207
      ]
    },
    {
      "Target": "Parameter",
      "Id": "ParamArmLowerLY",
      "FadeInTime": -1.0,
      "FadeOutTime": -1.0,
      "Segments": [
        0,
        -1.984,
        1,
        0.267,
        -2.295,
        0.533,
        -2.554,
        0.8,
        -2.554,
        1,
        1.467,
        -2.554,
        2.133,
        -0.934,
        2.8,
        -0.934,
        1,
        3.194,
        -0.934,
        3.589,
        -1.501,
        3.983,
        -1.964
      ]
    },
    {
      "Target": "Parameter",
      "Id": "ParamArmHandLZ",
      "FadeInTime": -1.0,
      "FadeOutTime": -1.0,
      "Segments": [
        0,
        -23.046,
        1,
        0.383,
        -26.131,
        0.767,
        -29.76,
        1.15,
        -29.76,
        1,
        1.817,
        -29.76,
        2.483,
        -18.783,
        3.15,
        -18.783,
        1,
        3.428,
        -18.783,
        3.705,
        -20.689,
        3.983,
        -22.912
      ]
    },
    {
      "Target": "Parameter",
      "Id": "ParamArmHandLX",
      "FadeInTime": -1.0,
      "FadeOutTime": -1.0,
      "Segments": [
        0,
        3.058,
        1,
        0.383,
        1.653,
        0.767,
        -0,
        1.15,
        0,
        1,
        1.817,
        0,
        2.483,
        5,
        3.15,
        5,
        1,
        3.428,
        5,
        3.705,
        4.132,
        3.983,
        3.119
      ]
    },
    {
      "Target": "Parameter",
      "Id": "ParamArmHandLY",
      "FadeInTime": -1.0,
      "FadeOutTime": -1.0,
      "Segments": [
        0,
        -0.358,
        1,
        0.383,
        -0.194,
        0.767,
        0,
        1.15,
        0,
        1,
        1.817,
        0,
        2.483,
        -0.586,
        3.15,
        -0.586,
        1,
        3.428,
        -0.586,
        3.705,
        -0.484,
        3.983,
        -0.366
      ]
    },
    {
      "Target": "Parameter",
      "Id": "Param4",
      "FadeInTime": -1.0,
      "FadeOutTime": -1.0,
      "Segments": [
        0,
        0.007,
        1,
        0.383,
        -3.212,
        0.767,
        -7,
        1.15,
        -7,
        1,
        1.817,
        -7,
        2.483,
        4.456,
        3.15,
        4.456,
        1,
        3.428,
        4.456,
        3.705,
        2.467,
        3.983,
        0.147
      ]
    },
    {
      "Target": "Parameter",
      "Id": "Param7",
      "FadeInTime": -1.0,
      "FadeOutTime": -1.0,
      "Segments": [
        0,
        0.999,
        1,
        0.383,
        1,
        0.767,
        1,
        1.15,
        1,
        1,
        1.817,
        1,
        2.483,
        0.999,
        3.15,
        0.999,
        2,
        3.983,
        0.999
      ]
    },
    {
      "Target": "Parameter",
      "Id": "Param6",
      "FadeInTime": -1.0,
      "FadeOutTime": -1.0,
      "Segments": [
        0,
        0.781,
        1,
        0.383,
        0.752,
        0.767,
        0.719,
        1.15,
        0.719,
        1,
        1.817,
        0.719,
        2.483,
        0.82,
        3.15,
        0.82,
        1,
        3.428,
        0.82,
        3.705,
        0.802,
        3.983,
        0.782
      ]
    },
    {
      "Target": "Parameter",
      "Id": "Param5",
      "FadeInTime": -1.0,
      "FadeOutTime": -1.0,
      "Segments": [
        0,
        0.2,
        1,
        0.383,
        0.145,
        0.767,
        0.08,
        1.15,
        0.08,
        1,
        1.817,
        0.08,
        2.483,
        0.276,
        3.15,
        0.276,
        1,
        3.428,
        0.276,
        3.705,
        0.242,
        3.983,
        0.202
      ]
    },
    {
      "Target": "Parameter",
      "Id": "ParamArmUpperRZ",
      "FadeInTime": -1.0,
      "FadeOutTime": -1.0,
      "Segments": [
        0,
        -25.137,
        1,
        0.267,
        -26.211,
        0.533,
        -27.105,
        0.8,
        -27.105,
        1,
        1.467,
        -27.105,
        2.133,
        -21.515,
        2.8,
        -21.515,
        1,
        3.194,
        -21.515,
        3.589,
        -23.472,
        3.983,
        -25.07
      ]
    },
    {
      "Target": "Parameter",
      "Id": "ParamArmUpperRX",
      "FadeInTime": -1.0,
      "FadeOutTime": -1.0,
      "Segments": [
        0,
        -3.92,
        1,
        0.267,
        -11.6,
        0.533,
        -18,
        0.8,
        -18,
        1,
        1.467,
        -18,
        2.133,
        22,
        2.8,
        22,
        1,
        3.194,
        22,
        3.589,
        7.997,
        3.983,
        -3.438
      ]
    },
    {
      "Target": "Parameter",
      "Id": "ParamArmUpperRY",
      "FadeInTime": -1.0,
      "FadeOutTime": -1.0,
      "Segments": [
        0,
        0.211,
        1,
        0.267,
        0.096,
        0.533,
        0,
        0.8,
        0,
        1,
        1.467,
        0,
        2.133,
        0.6,
        2.8,
        0.6,
        1,
        3.194,
        0.6,
        3.589,
        0.39,
        3.983,
        0.218
      ]
    },
    {
      "Target": "Parameter",
      "Id": "ParamArmLowerRZ",
      "FadeInTime": -1.0,
      "FadeOutTime": -1.0,
      "Segments": [
        0,
        -87.268,
        1,
        0.411,
        -89.3,
        0.822,
        -91.95,
        1.233,
        -91.95,
        1,
        1.9,
        -91.95,
        2.566,
        -84.981,
        3.233,
        -84.981,
        1,
        3.483,
        -84.981,
        3.733,
        -85.961,
        3.983,
        -87.186
      ]
    },
    {
      "Target": "Parameter",
      "Id": "ParamArmLowerRX",
      "FadeInTime": -1.0,
      "FadeOutTime": -1.0,
      "Segments": [
        0,
        9.269,
        1,
        0.411,
        -2.999,
        0.822,
        -19,
        1.233,
        -19,
        1,
        1.9,
        -19,
        2.566,
        23.078,
        3.233,
        23.078,
        1,
        3.483,
        23.078,
        3.733,
        17.161,
        3.983,
        9.764
      ]
    },
    {
      "Target": "Parameter",
      "Id": "ParamArmLowerRY",
      "FadeInTime": -1.0,
      "FadeOutTime": -1.0,
      "Segments": [
        0,
        0.645,
        1,
        0.411,
        0.365,
        0.822,
        0,
        1.233,
        0,
        1,
        1.9,
        0,
        2.566,
        0.96,
        3.233,
        0.96,
        1,
        3.483,
        0.96,
        3.733,
        0.825,
        3.983,
        0.656
      ]
    },
    {
      "Target": "Parameter",
      "Id": "ParamArmHandRZ",
      "FadeInTime": -1.0,
      "FadeOutTime": -1.0,
      "Segments": [
        0,
        -16.066,
        1,
        0.583,
        -18.053,
        1.167,
        -26,
        1.75,
        -26,
        1,
        2.417,
        -26,
        3.083,
        -15.62,
        3.75,
        -15.62,
        1,
        3.828,
        -15.62,
        3.905,
        -15.761,
        3.983,
        -16.011
      ]
    },
    {
      "Target": "Parameter",
      "Id": "ParamArmHandRX",
      "FadeInTime": -1.0,
      "FadeOutTime": -1.0,
      "Segments": [
        0,
        -30,
        2,
        1.75,
        -30,
        2,
        3.75,
        -30,
        1,
        3.828,
        -30,
        3.905,
        -29.687,
        3.983,
        -29.134
      ]
    },
    {
      "Target": "Parameter",
      "Id": "ParamArmHandRY",
      "FadeInTime": -1.0,
      "FadeOutTime": -1.0,
      "Segments": [
        0,
        -6.916,
        1,
        0.583,
        -11.533,
        1.167,
        -30,
        1.75,
        -30,
        1,
        2.417,
        -30,
        3.083,
        -5.88,
        3.75,
        -5.88,
        1,
        3.828,
        -5.88,
        3.905,
        -6.208,
        3.983,
        -6.788
      ]
    },
    {
      "Target": "Parameter",
      "Id": "Param9",
      "FadeInTime": -1.0,
      "FadeOutTime": -1.0,
      "Segments": [
        0,
        -0.268,
        1,
        0.583,
        -1.014,
        1.167,
        -4,
        1.75,
        -4,
        1,
        2.417,
        -4,
        3.083,
        -0.1,
        3.75,
        -0.1,
        1,
        3.828,
        -0.1,
        3.905,
        -0.271,
        3.983,
        -0.572
      ]
    },
    {
      "Target": "Parameter",
      "Id": "Param16",
      "FadeInTime": -1.0,
      "FadeOutTime": -1.0,
      "Segments": [
        0,
        -9.902,
        1,
        0.583,
        -13.922,
        1.167,
        -30,
        1.75,
        -30,
        1,
        2.417,
        -30,
        3.083,
        -9,
        3.75,
        -9,
        1,
        3.828,
        -9,
        3.905,
        -9.286,
        3.983,
        -9.791
      ]
    },
    {
      "Target": "Parameter",
      "Id": "Param11",
      "FadeInTime": -1.0,
      "FadeOutTime": -1.0,
      "Segments": [
        0,
        0.342,
        1,
        0.583,
        0.313,
        1.167,
        0.2,
        1.75,
        0.2,
        1,
        2.417,
        0.2,
        3.083,
        0.348,
        3.75,
        0.348,
        1,
        3.828,
        0.348,
        3.905,
        0.346,
        3.983,
        0.342
      ]
    },
    {
      "Target": "Parameter",
      "Id": "Param15",
      "FadeInTime": -1.0,
      "FadeOutTime": -1.0,
      "Segments": [
        0,
        -18.516,
        1,
        0.583,
        -20.813,
        1.167,
        -30,
        1.75,
        -30,
        1,
        2.417,
        -30,
        3.083,
        -18,
        3.75,
        -18,
        1,
        3.828,
        -18,
        3.905,
        -18.163,
        3.983,
        -18.452
      ]
    },
    {
      "Target": "Parameter",
      "Id": "Param89",
      "FadeInTime": -1.0,
      "FadeOutTime": -1.0,
      "Segments": [
        0,
        0.968,
        1,
        0.333,
        -6.012,
        0.667,
        -12.992,
        1,
        -12.992,
        1,
        1.667,
        -12.992,
        2.333,
        14.929,
        3,
        14.929,
        1,
        3.328,
        14.929,
        3.655,
        8.18,
        3.983,
        1.317
      ]
    },
    {
      "Target": "Parameter",
      "Id": "Param90",
      "FadeInTime": -1.0,
      "FadeOutTime": -1.0,
      "Segments": [
        0,
        15.723,
        1,
        0.033,
        15.856,
        0.067,
        15.925,
        0.1,
        15.925,
        1,
        0.767,
        15.925,
        1.433,
        -11.994,
        2.1,
        -11.994,
        1,
        2.728,
        -11.994,
        3.355,
        12.763,
        3.983,
        15.651
      ]
    },
    {
      "Target": "Parameter",
      "Id": "Param",
      "FadeInTime": -1.0,
      "FadeOutTime": -1.0,
      "Segments": [
        0,
        2.549,
        1,
        0.372,
        -7.089,
        0.745,
        -18,
        1.117,
        -18,
        1,
        1.784,
        -18,
        2.45,
        17,
        3.117,
        17,
        1,
        3.406,
        17,
        3.694,
        10.428,
        3.983,
        2.979
      ]
    },
    {
      "Target": "Parameter",
      "Id": "Param91",
      "FadeInTime": -1.0,
      "FadeOutTime": -1.0,
      "Segments": [
        0,
        28.601,
        1,
        0.033,
        28.862,
        0.067,
        29,
        0.1,
        29,
        1,
        0.767,
        29,
        1.433,
        -26,
        2.1,
        -26,
        1,
        2.728,
        -26,
        3.355,
        22.771,
        3.983,
        28.46
      ]
    },
    {
      "Target": "Parameter",
      "Id": "Param92",
      "FadeInTime": -1.0,
      "FadeOutTime": -1.0,
      "Segments": [
        0,
        3.016,
        1,
        0.456,
        -3.194,
        0.911,
        -13,
        1.367,
        -13,
        1,
        2.034,
        -13,
        2.7,
        8,
        3.367,
        8,
        1,
        3.572,
        8,
        3.778,
        6.004,
        3.983,
        3.242
      ]
    },
    {
      "Target": "Parameter",
      "Id": "Param93",
      "FadeInTime": -1.0,
      "FadeOutTime": -1.0,
      "Segments": [
        0,
        16.107,
        1,
        0.106,
        17.922,
        0.211,
        19,
        0.317,
        19,
        1,
        0.984,
        19,
        1.65,
        -24,
        2.317,
        -24,
        1,
        2.872,
        -24,
        3.428,
        5.861,
        3.983,
        15.815
      ]
    },
    {
      "Target": "Parameter",
      "Id": "Param94",
      "FadeInTime": -1.0,
      "FadeOutTime": -1.0,
      "Segments": [
        0,
        -3.515,
        1,
        0.294,
        -6.569,
        0.589,
        -9.303,
        0.883,
        -9.303,
        1,
        1.55,
        -9.303,
        2.216,
        4.714,
        2.883,
        4.714,
        1,
        3.25,
        4.714,
        3.616,
        0.474,
        3.983,
        -3.342
      ]
    },
    {
      "Target": "Parameter",
      "Id": "Param95",
      "FadeInTime": -1.0,
      "FadeOutTime": -1.0,
      "Segments": [
        0,
        28.839,
        1,
        0.611,
        20.576,
        1.222,
        -29,
        1.833,
        -29,
        1,
        2.5,
        -29,
        3.166,
        30,
        3.833,
        30,
        1,
        3.883,
        30,
        3.933,
        29.668,
        3.983,
        29.054
      ]
    },
    {
      "Target": "Parameter",
      "Id": "ParamLegUpperLZ",
      "FadeInTime": -1.0,
      "FadeOutTime": -1.0,
      "Segments": [
        0,
        -11,
        1,
        0.667,
        -11,
        1.333,
        -10.28,
        2,
        -10.28,
        1,
        2.661,
        -10.28,
        3.322,
        -10.988,
        3.983,
        -11
      ]
    },
    {
      "Target": "Parameter",
      "Id": "ParamLegUpperLX",
      "FadeInTime": -1.0,
      "FadeOutTime": -1.0,
      "Segments": [
        0,
        -19,
        1,
        0.667,
        -19,
        1.333,
        5,
        2,
        5,
        1,
        2.661,
        5,
        3.322,
        -18.602,
        3.983,
        -18.995
      ]
    },
    {
      "Target": "Parameter",
      "Id": "ParamLegUpperLY",
      "FadeInTime": -1.0,
      "FadeOutTime": -1.0,
      "Segments": [
        0,
        30,
        1,
        0.667,
        30,
        1.333,
        22.68,
        2,
        22.68,
        1,
        2.661,
        22.68,
        3.322,
        29.879,
        3.983,
        29.998
      ]
    },
    {
      "Target": "Parameter",
      "Id": "ParamLegLowerLZ",
      "FadeInTime": -1.0,
      "FadeOutTime": -1.0,
      "Segments": [
        0,
        30,
        1,
        0.667,
        30,
        1.333,
        29.34,
        2,
        29.34,
        1,
        2.661,
        29.34,
        3.322,
        29.989,
        3.983,
        30
      ]
    },
    {
      "Target": "Parameter",
      "Id": "ParamLegLowerLX",
      "FadeInTime": -1.0,
      "FadeOutTime": -1.0,
      "Segments": [
        0,
        -30,
        1,
        0.667,
        -30,
        1.333,
        -6,
        2,
        -6,
        1,
        2.661,
        -6,
        3.322,
        -29.602,
        3.983,
        -29.995
      ]
    },
    {
      "Target": "Parameter",
      "Id": "ParamLegLowerLY",
      "FadeInTime": -1.0,
      "FadeOutTime": -1.0,
      "Segments": [
        0,
        -18,
        1,
        0.667,
        -18,
        1.333,
        -16.5,
        2,
        -16.5,
        1,
        2.661,
        -16.5,
        3.322,
        -17.975,
        3.983,
        -18
      ]
    },
    {
      "Target": "Parameter",
      "Id": "ParamLegUpperRZ",
      "FadeInTime": -1.0,
      "FadeOutTime": -1.0,
      "Segments": [
        0,
        -1,
        1,
        0.667,
        -1,
        1.333,
        -0.16,
        2,
        -0.16,
        1,
        2.661,
        -0.16,
        3.322,
        -0.986,
        3.983,
        -1
      ]
    },
    {
      "Target": "Parameter",
      "Id": "ParamLegUpperRX",
      "FadeInTime": -1.0,
      "FadeOutTime": -1.0,
      "Segments": [
        0,
        30,
        1,
        0.667,
        30,
        1.333,
        -2,
        2,
        -2,
        1,
        2.661,
        -2,
        3.322,
        29.469,
        3.983,
        29.993
      ]
    },
    {
      "Target": "Parameter",
      "Id": "ParamLegUpperRY",
      "FadeInTime": -1.0,
      "FadeOutTime": -1.0,
      "Segments": [
        0,
        23.7,
        1,
        0.667,
        23.7,
        1.333,
        30,
        2,
        30,
        1,
        2.661,
        30,
        3.322,
        23.805,
        3.983,
        23.701
      ]
    },
    {
      "Target": "Parameter",
      "Id": "ParamLegLowerRZ",
      "FadeInTime": -1.0,
      "FadeOutTime": -1.0,
      "Segments": [
        0,
        30,
        1,
        0.667,
        30,
        1.333,
        23.88,
        2,
        23.88,
        1,
        2.661,
        23.88,
        3.322,
        29.898,
        3.983,
        29.999
      ]
    },
    {
      "Target": "Parameter",
      "Id": "ParamLegLowerRX",
      "FadeInTime": -1.0,
      "FadeOutTime": -1.0,
      "Segments": [
        0,
        22,
        1,
        0.667,
        22,
        1.333,
        -9,
        2,
        -9,
        1,
        2.661,
        -9,
        3.322,
        21.486,
        3.983,
        21.994
      ]
    },
    {
      "Target": "Parameter",
      "Id": "ParamLegFootRZ",
      "FadeInTime": -1.0,
      "FadeOutTime": -1.0,
      "Segments": [
        0,
        7.28,
        1,
        0.667,
        7.28,
        1.333,
        14.48,
        2,
        14.48,
        1,
        2.661,
        14.48,
        3.322,
        7.399,
        3.983,
        7.281
      ]
    },
    {
      "Target": "Parameter",
      "Id": "ParamLegFootRY",
      "FadeInTime": -1.0,
      "FadeOutTime": -1.0,
      "Segments": [
        0,
        -27,
        1,
        0.667,
        -27,
        1.333,
        -19.16,
        2,
        -19.16,
        1,
        2.661,
        -19.16,
        3.322,
        -26.87,
        3.983,
        -26.998
      ]
    },
    {
      "Target": "Parameter",
      "Id": "EyeTracking_ParamAngleX",
      "FadeInTime": -1.0,
      "FadeOutTime": -1.0,
      "Segments": [
        0,
        18.005,
        1,
        1.328,
        18.005,
        2.655,
        18.005,
        3.983,
        18.005
      ]
    },
    {
      "Target": "Parameter",
      "Id": "ParamEyeLOpen",
      "FadeInTime": -1.0,
      "FadeOutTime": -1.0,
      "Segments": [
        0,
        1,
        1,
        1.328,
        1,
        2.655,
        1,
        3.983,
        1
      ]
    },
    {
      "Target": "Parameter",
      "Id": "ParamEyeLSmile",
      "FadeInTime": -1.0,
      "FadeOutTime": -1.0,
      "Segments": [
        0,
        0,
        1,
        1.328,
        0,
        2.655,
        0,
        3.983,
        0
      ]
    },
    {
      "Target": "Parameter",
      "Id": "ParamEyeROpen",
      "FadeInTime": -1.0,
      "FadeOutTime": -1.0,
      "Segments": [
        0,
        1,
        1,
        1.328,
        1,
        2.655,
        1,
        3.983,
        1
      ]
    },
    {
      "Target": "Parameter",
      "Id": "ParamEyeRSmile",
      "FadeInTime": -1.0,
      "FadeOutTime": -1.0,
      "Segments": [
        0,
        0,
        1,
        1.328,
        0,
        2.655,
        0,
        3.983,
        0
      ]
    },
    {
      "Target": "Parameter",
      "Id": "Param114",
      "FadeInTime": -1.0,
      "FadeOutTime": -1.0,
      "Segments": [
        0,
        0,
        1,
        1.328,
        0,
        2.655,
        0,
        3.983,
        0
      ]
    },
    {
      "Target": "Parameter",
      "Id": "Param115",
      "FadeInTime": -1.0,
      "FadeOutTime": -1.0,
      "Segments": [
        0,
        0,
        1,
        1.328,
        0,
        2.655,
        0,
        3.983,
        0
      ]
    },
    {
      "Target": "Parameter",
      "Id": "Param116",
      "FadeInTime": -1.0,
      "FadeOutTime": -1.0,
      "Segments": [
        0,
        0,
        1,
        1.328,
        0,
        2.655,
        0,
        3.983,
        0
      ]
    },
    {
      "Target": "Parameter",
      "Id": "EyeTracking_ParamEyeBallX",
      "FadeInTime": -1.0,
      "FadeOutTime": -1.0,
      "Segments": [
        0,
        -0.2,
        1,
        1.328,
        -0.2,
        2.655,
        -0.2,
        3.983,
        -0.2
      ]
    },
    {
      "Target": "Parameter",
      "Id": "EyeTracking_ParamEyeBallY",
      "FadeInTime": -1.0,
      "FadeOutTime": -1.0,
      "Segments": [
        0,
        -0.3,
        1,
        1.328,
        -0.3,
        2.655,
        -0.3,
        3.983,
        -0.3
      ]
    },
    {
      "Target": "Parameter",
      "Id": "Param150",
      "FadeInTime": -1.0,
      "FadeOutTime": -1.0,
      "Segments": [
        0,
        1,
        1,
        1.328,
        1,
        2.655,
        1,
        3.983,
        1
      ]
    },
    {
      "Target": "Parameter",
      "Id": "Param171",
      "FadeInTime": -1.0,
      "FadeOutTime": -1.0,
      "Segments": [
        0,
        1,
        1,
        1.328,
        1,
        2.655,
        1,
        3.983,
        1
      ]
    },
    {
      "Target": "Parameter",
      "Id": "ParamBrowLY",
      "FadeInTime": -1.0,
      "FadeOutTime": -1.0,
      "Segments": [
        0,
        -0.154,
        1,
        1.328,
        -0.154,
        2.655,
        -0.154,
        3.983,
        -0.154
      ]
    },
    {
      "Target": "Parameter",
      "Id": "ParamBrowLAngle",
      "FadeInTime": -1.0,
      "FadeOutTime": -1.0,
      "Segments": [
        0,
        0,
        1,
        1.328,
        0,
        2.655,
        0,
        3.983,
        0
      ]
    },
    {
      "Target": "Parameter",
      "Id": "ParamBrowLForm",
      "FadeInTime": -1.0,
      "FadeOutTime": -1.0,
      "Segments": [
        0,
        0,
        1,
        1.328,
        0,
        2.655,
        0,
        3.983,
        0
      ]
    },
    {
      "Target": "Parameter",
      "Id": "ParamBrowRY",
      "FadeInTime": -1.0,
      "FadeOutTime": -1.0,
      "Segments": [
        0,
        0,
        1,
        1.328,
        0,
        2.655,
        0,
        3.983,
        0
      ]
    },
    {
      "Target": "Parameter",
      "Id": "ParamBrowRAngle",
      "FadeInTime": -1.0,
      "FadeOutTime": -1.0,
      "Segments": [
        0,
        0,
        1,
        1.328,
        0,
        2.655,
        0,
        3.983,
        0
      ]
    },
    {
      "Target": "Parameter",
      "Id": "ParamBrowRForm",
      "FadeInTime": -1.0,
      "FadeOutTime": -1.0,
      "Segments": [
        0,
        0,
        1,
        1.328,
        0,
        2.655,
        0,
        3.983,
        0
      ]
    },
    {
      "Target": "Parameter",
      "Id": "ParamMouthForm",
      "FadeInTime": -1.0,
      "FadeOutTime": -1.0,
      "Segments": [
        0,
        -0.706,
        1,
        1.328,
        -0.706,
        2.655,
        -0.706,
        3.983,
        -0.706
      ]
    },
    {
      "Target": "Parameter",
      "Id": "Param143",
      "FadeInTime": -1.0,
      "FadeOutTime": -1.0,
      "Segments": [
        0,
        0,
        1,
        1.328,
        0,
        2.655,
        0,
        3.983,
        0
      ]
    },
    {
      "Target": "Parameter",
      "Id": "ParamMouthOpenY",
      "FadeInTime": -1.0,
      "FadeOutTime": -1.0,
      "Segments": [
        0,
        0,
        1,
        1.328,
        0,
        2.655,
        0,
        3.983,
        0
      ]
    },
    {
      "Target": "Parameter",
      "Id": "ParamMouthSize",
      "FadeInTime": -1.0,
      "FadeOutTime": -1.0,
      "Segments": [
        0,
        0,
        1,
        1.328,
        0,
        2.655,
        0,
        3.983,
        0
      ]
    },
    {
      "Target": "Parameter",
      "Id": "Param99",
      "FadeInTime": -1.0,
      "FadeOutTime": -1.0,
      "Segments": [
        0,
        0,
        1,
        1.328,
        0,
        2.655,
        0,
        3.983,
        0
      ]
    },
    {
      "Target": "Parameter",
      "Id": "ParamCheek",
      "FadeInTime": -1.0,
      "FadeOutTime": -1.0,
      "Segments": [
        0,
        0,
        1,
        1.328,
        0,
        2.655,
        0,
        3.983,
        0
      ]
    },
    {
      "Target": "Parameter",
      "Id": "ParamTearsIn",
      "FadeInTime": -1.0,
      "FadeOutTime": -1.0,
      "Segments": [
        0,
        0,
        1,
        1.328,
        0,
        2.655,
        0,
        3.983,
        0
      ]
    },
    {
      "Target": "Parameter",
      "Id": "ParamTearsYure1",
      "FadeInTime": -1.0,
      "FadeOutTime": -1.0,
      "Segments": [
        0,
        0,
        1,
        1.328,
        0,
        2.655,
        0,
        3.983,
        0
      ]
    },
    {
      "Target": "Parameter",
      "Id": "ParamTearsYure2",
      "FadeInTime": -1.0,
      "FadeOutTime": -1.0,
      "Segments": [
        0,
        0,
        1,
        1.328,
        0,
        2.655,
        0,
        3.983,
        0
      ]
    },
    {
      "Target": "Parameter",
      "Id": "ParamTearsL",
      "FadeInTime": -1.0,
      "FadeOutTime": -1.0,
      "Segments": [
        0,
        0,
        1,
        1.328,
        0,
        2.655,
        0,
        3.983,
        0
      ]
    },
    {
      "Target": "Parameter",
      "Id": "ParamTearsR",
      "FadeInTime": -1.0,
      "FadeOutTime": -1.0,
      "Segments": [
        0,
        0,
        1,
        1.328,
        0,
        2.655,
        0,
        3.983,
        0
      ]
    },
    {
      "Target": "Parameter",
      "Id": "ParamTearsDrop",
      "FadeInTime": -1.0,
      "FadeOutTime": -1.0,
      "Segments": [
        0,
        0,
        1,
        1.328,
        0,
        2.655,
        0,
        3.983,
        0
      ]
    },
    {
      "Target": "Parameter",
      "Id": "Param100",
      "FadeInTime": -1.0,
      "FadeOutTime": -1.0,
      "Segments": [
        0,
        0,
        1,
        1.328,
        0,
        2.655,
        0,
        3.983,
        0
      ]
    },
    {
      "Target": "Parameter",
      "Id": "ParamShoulderL",
      "FadeInTime": -1.0,
      "FadeOutTime": -1.0,
      "Segments": [
        0,
        11,
        1,
        1.328,
        11,
        2.655,
        11,
        3.983,
        11
      ]
    },
    {
      "Target": "Parameter",
      "Id": "ParamShoulderR",
      "FadeInTime": -1.0,
      "FadeOutTime": -1.0,
      "Segments": [
        0,
        -26.761,
        1,
        1.328,
        -26.761,
        2.655,
        -26.761,
        3.983,
        -26.761
      ]
    },
    {
      "Target": "Parameter",
      "Id": "Param129",
      "FadeInTime": -1.0,
      "FadeOutTime": -1.0,
      "Segments": [
        0,
        0,
        1,
        1.328,
        0,
        2.655,
        0,
        3.983,
        0
      ]
    },
    {
      "Target": "Parameter",
      "Id": "Param8",
      "FadeInTime": -1.0,
      "FadeOutTime": -1.0,
      "Segments": [
        0,
        0,
        1,
        1.328,
        0,
        2.655,
        0,
        3.983,
        0
      ]
    },
    {
      "Target": "Parameter",
      "Id": "Param10",
      "FadeInTime": -1.0,
      "FadeOutTime": -1.0,
      "Segments": [
        0,
        0,
        1,
        1.328,
        0,
        2.655,
        0,
        3.983,
        0
      ]
    },
    {
      "Target": "Parameter",
      "Id": "Param145",
      "FadeInTime": -1.0,
      "FadeOutTime": -1.0,
      "Segments": [
        0,
        0,
        1,
        1.328,
        0,
        2.655,
        0,
        3.983,
        0
      ]
    },
    {
      "Target": "Parameter",
      "Id": "Param14",
      "FadeInTime": -1.0,
      "FadeOutTime": -1.0,
      "Segments": [
        0,
        0,
        1,
        1.328,
        0,
        2.655,
        0,
        3.983,
        0
      ]
    },
    {
      "Target": "Parameter",
      "Id": "Param130",
      "FadeInTime": -1.0,
      "FadeOutTime": -1.0,
      "Segments": [
        0,
        0,
        1,
        1.328,
        0,
        2.655,
        0,
        3.983,
        0
      ]
    },
    {
      "Target": "Parameter",
      "Id": "Param12",
      "FadeInTime": -1.0,
      "FadeOutTime": -1.0,
      "Segments": [
        0,
        1,
        1,
        1.328,
        1,
        2.655,
        1,
        3.983,
        1
      ]
    },
    {
      "Target": "Parameter",
      "Id": "Param13",
      "FadeInTime": -1.0,
      "FadeOutTime": -1.0,
      "Segments": [
        0,
        0,
        1,
        1.328,
        0,
        2.655,
        0,
        3.983,
        0
      ]
    },
    {
      "Target": "Parameter",
      "Id": "Param144",
      "FadeInTime": -1.0,
      "FadeOutTime": -1.0,
      "Segments": [
        0,
        0,
        1,
        1.328,
        0,
        2.655,
        0,
        3.983,
        0
      ]
    },
    {
      "Target": "Parameter",
      "Id": "Param23",
      "FadeInTime": -1.0,
      "FadeOutTime": -1.0,
      "Segments": [
        0,
        1,
        1,
        1.328,
        1,
        2.655,
        1,
        3.983,
        1
      ]
    },
    {
      "Target": "Parameter",
      "Id": "Param25",
      "FadeInTime": -1.0,
      "FadeOutTime": -1.0,
      "Segments": [
        0,
        0,
        1,
        1.328,
        0,
        2.655,
        0,
        3.983,
        0
      ]
    },
    {
      "Target": "Parameter",
      "Id": "Param26",
      "FadeInTime": -1.0,
      "FadeOutTime": -1.0,
      "Segments": [
        0,
        0,
        1,
        1.328,
        0,
        2.655,
        0,
        3.983,
        0
      ]
    },
    {
      "Target": "Parameter",
      "Id": "Param24",
      "FadeInTime": -1.0,
      "FadeOutTime": -1.0,
      "Segments": [
        0,
        1,
        1,
        1.328,
        1,
        2.655,
        1,
        3.983,
        1
      ]
    },
    {
      "Target": "Parameter",
      "Id": "Param27",
      "FadeInTime": -1.0,
      "FadeOutTime": -1.0,
      "Segments": [
        0,
        0,
        1,
        1.328,
        0,
        2.655,
        0,
        3.983,
        0
      ]
    },
    {
      "Target": "Parameter",
      "Id": "Param28",
      "FadeInTime": -1.0,
      "FadeOutTime": -1.0,
      "Segments": [
        0,
        0,
        1,
        1.328,
        0,
        2.655,
        0,
        3.983,
        0
      ]
    },
    {
      "Target": "Parameter",
      "Id": "Param17",
      "FadeInTime": -1.0,
      "FadeOutTime": -1.0,
      "Segments": [
        0,
        -30,
        1,
        1.328,
        -30,
        2.655,
        -30,
        3.983,
        -30
      ]
    },
    {
      "Target": "Parameter",
      "Id": "Param18",
      "FadeInTime": -1.0,
      "FadeOutTime": -1.0,
      "Segments": [
        0,
        0,
        1,
        1.328,
        0,
        2.655,
        0,
        3.983,
        0
      ]
    },
    {
      "Target": "Parameter",
      "Id": "Param19",
      "FadeInTime": -1.0,
      "FadeOutTime": -1.0,
      "Segments": [
        0,
        -1,
        1,
        1.328,
        -1,
        2.655,
        -1,
        3.983,
        -1
      ]
    },
    {
      "Target": "Parameter",
      "Id": "Param117",
      "FadeInTime": -1.0,
      "FadeOutTime": -1.0,
      "Segments": [
        0,
        -24.9,
        1,
        1.328,
        -24.9,
        2.655,
        -24.9,
        3.983,
        -24.9
      ]
    },
    {
      "Target": "Parameter",
      "Id": "Param118",
      "FadeInTime": -1.0,
      "FadeOutTime": -1.0,
      "Segments": [
        0,
        0.36,
        1,
        1.328,
        0.36,
        2.655,
        0.36,
        3.983,
        0.36
      ]
    },
    {
      "Target": "Parameter",
      "Id": "Param119",
      "FadeInTime": -1.0,
      "FadeOutTime": -1.0,
      "Segments": [
        0,
        8,
        1,
        1.328,
        8,
        2.655,
        8,
        3.983,
        8
      ]
    },
    {
      "Target": "Parameter",
      "Id": "Param29",
      "FadeInTime": -1.0,
      "FadeOutTime": -1.0,
      "Segments": [
        0,
        30,
        1,
        1.328,
        30,
        2.655,
        30,
        3.983,
        30
      ]
    },
    {
      "Target": "Parameter",
      "Id": "Param20",
      "FadeInTime": -1.0,
      "FadeOutTime": -1.0,
      "Segments": [
        0,
        30,
        1,
        1.328,
        30,
        2.655,
        30,
        3.983,
        30
      ]
    },
    {
      "Target": "Parameter",
      "Id": "Param21",
      "FadeInTime": -1.0,
      "FadeOutTime": -1.0,
      "Segments": [
        0,
        -3,
        1,
        1.328,
        -3,
        2.655,
        -3,
        3.983,
        -3
      ]
    },
    {
      "Target": "Parameter",
      "Id": "Param22",
      "FadeInTime": -1.0,
      "FadeOutTime": -1.0,
      "Segments": [
        0,
        -30,
        1,
        1.328,
        -30,
        2.655,
        -30,
        3.983,
        -30
      ]
    },
    {
      "Target": "Parameter",
      "Id": "Param31",
      "FadeInTime": -1.0,
      "FadeOutTime": -1.0,
      "Segments": [
        0,
        0,
        1,
        1.328,
        0,
        2.655,
        0,
        3.983,
        0
      ]
    },
    {
      "Target": "Parameter",
      "Id": "Param33",
      "FadeInTime": -1.0,
      "FadeOutTime": -1.0,
      "Segments": [
        0,
        0,
        1,
        1.328,
        0,
        2.655,
        0,
        3.983,
        0
      ]
    },
    {
      "Target": "Parameter",
      "Id": "Param34",
      "FadeInTime": -1.0,
      "FadeOutTime": -1.0,
      "Segments": [
        0,
        0,
        1,
        1.328,
        0,
        2.655,
        0,
        3.983,
        0
      ]
    },
    {
      "Target": "Parameter",
      "Id": "Param120",
      "FadeInTime": -1.0,
      "FadeOutTime": -1.0,
      "Segments": [
        0,
        0,
        1,
        1.328,
        0,
        2.655,
        0,
        3.983,
        0
      ]
    },
    {
      "Target": "Parameter",
      "Id": "Param121",
      "FadeInTime": -1.0,
      "FadeOutTime": -1.0,
      "Segments": [
        0,
        0,
        1,
        1.328,
        0,
        2.655,
        0,
        3.983,
        0
      ]
    },
    {
      "Target": "Parameter",
      "Id": "Param122",
      "FadeInTime": -1.0,
      "FadeOutTime": -1.0,
      "Segments": [
        0,
        0,
        1,
        1.328,
        0,
        2.655,
        0,
        3.983,
        0
      ]
    },
    {
      "Target": "Parameter",
      "Id": "Param30",
      "FadeInTime": -1.0,
      "FadeOutTime": -1.0,
      "Segments": [
        0,
        0,
        1,
        1.328,
        0,
        2.655,
        0,
        3.983,
        0
      ]
    },
    {
      "Target": "Parameter",
      "Id": "Param35",
      "FadeInTime": -1.0,
      "FadeOutTime": -1.0,
      "Segments": [
        0,
        0,
        1,
        1.328,
        0,
        2.655,
        0,
        3.983,
        0
      ]
    },
    {
      "Target": "Parameter",
      "Id": "Param36",
      "FadeInTime": -1.0,
      "FadeOutTime": -1.0,
      "Segments": [
        0,
        0,
        1,
        1.328,
        0,
        2.655,
        0,
        3.983,
        0
      ]
    },
    {
      "Target": "Parameter",
      "Id": "Param32",
      "FadeInTime": -1.0,
      "FadeOutTime": -1.0,
      "Segments": [
        0,
        0,
        1,
        1.328,
        0,
        2.655,
        0,
        3.983,
        0
      ]
    },
    {
      "Target": "Parameter",
      "Id": "Param38",
      "FadeInTime": -1.0,
      "FadeOutTime": -1.0,
      "Segments": [
        0,
        0,
        1,
        1.328,
        0,
        2.655,
        0,
        3.983,
        0
      ]
    },
    {
      "Target": "Parameter",
      "Id": "Param39",
      "FadeInTime": -1.0,
      "FadeOutTime": -1.0,
      "Segments": [
        0,
        0,
        1,
        1.328,
        0,
        2.655,
        0,
        3.983,
        0
      ]
    },
    {
      "Target": "Parameter",
      "Id": "Param40",
      "FadeInTime": -1.0,
      "FadeOutTime": -1.0,
      "Segments": [
        0,
        0,
        1,
        1.328,
        0,
        2.655,
        0,
        3.983,
        0
      ]
    },
    {
      "Target": "Parameter",
      "Id": "Param123",
      "FadeInTime": -1.0,
      "FadeOutTime": -1.0,
      "Segments": [
        0,
        0,
        1,
        1.328,
        0,
        2.655,
        0,
        3.983,
        0
      ]
    },
    {
      "Target": "Parameter",
      "Id": "Param124",
      "FadeInTime": -1.0,
      "FadeOutTime": -1.0,
      "Segments": [
        0,
        0,
        1,
        1.328,
        0,
        2.655,
        0,
        3.983,
        0
      ]
    },
    {
      "Target": "Parameter",
      "Id": "Param125",
      "FadeInTime": -1.0,
      "FadeOutTime": -1.0,
      "Segments": [
        0,
        0,
        1,
        1.328,
        0,
        2.655,
        0,
        3.983,
        0
      ]
    },
    {
      "Target": "Parameter",
      "Id": "Param37",
      "FadeInTime": -1.0,
      "FadeOutTime": -1.0,
      "Segments": [
        0,
        0,
        1,
        1.328,
        0,
        2.655,
        0,
        3.983,
        0
      ]
    },
    {
      "Target": "Parameter",
      "Id": "Param41",
      "FadeInTime": -1.0,
      "FadeOutTime": -1.0,
      "Segments": [
        0,
        0,
        1,
        1.328,
        0,
        2.655,
        0,
        3.983,
        0
      ]
    },
    {
      "Target": "Parameter",
      "Id": "Param42",
      "FadeInTime": -1.0,
      "FadeOutTime": -1.0,
      "Segments": [
        0,
        0,
        1,
        1.328,
        0,
        2.655,
        0,
        3.983,
        0
      ]
    },
    {
      "Target": "Parameter",
      "Id": "Param43",
      "FadeInTime": -1.0,
      "FadeOutTime": -1.0,
      "Segments": [
        0,
        0,
        1,
        1.328,
        0,
        2.655,
        0,
        3.983,
        0
      ]
    },
    {
      "Target": "Parameter",
      "Id": "Param45",
      "FadeInTime": -1.0,
      "FadeOutTime": -1.0,
      "Segments": [
        0,
        0,
        1,
        1.328,
        0,
        2.655,
        0,
        3.983,
        0
      ]
    },
    {
      "Target": "Parameter",
      "Id": "Param46",
      "FadeInTime": -1.0,
      "FadeOutTime": -1.0,
      "Segments": [
        0,
        0,
        1,
        1.328,
        0,
        2.655,
        0,
        3.983,
        0
      ]
    },
    {
      "Target": "Parameter",
      "Id": "Param47",
      "FadeInTime": -1.0,
      "FadeOutTime": -1.0,
      "Segments": [
        0,
        0,
        1,
        1.328,
        0,
        2.655,
        0,
        3.983,
        0
      ]
    },
    {
      "Target": "Parameter",
      "Id": "Param126",
      "FadeInTime": -1.0,
      "FadeOutTime": -1.0,
      "Segments": [
        0,
        0,
        1,
        1.328,
        0,
        2.655,
        0,
        3.983,
        0
      ]
    },
    {
      "Target": "Parameter",
      "Id": "Param127",
      "FadeInTime": -1.0,
      "FadeOutTime": -1.0,
      "Segments": [
        0,
        0,
        1,
        1.328,
        0,
        2.655,
        0,
        3.983,
        0
      ]
    },
    {
      "Target": "Parameter",
      "Id": "Param128",
      "FadeInTime": -1.0,
      "FadeOutTime": -1.0,
      "Segments": [
        0,
        0,
        1,
        1.328,
        0,
        2.655,
        0,
        3.983,
        0
      ]
    },
    {
      "Target": "Parameter",
      "Id": "Param44",
      "FadeInTime": -1.0,
      "FadeOutTime": -1.0,
      "Segments": [
        0,
        0,
        1,
        1.328,
        0,
        2.655,
        0,
        3.983,
        0
      ]
    },
    {
      "Target": "Parameter",
      "Id": "Param48",
      "FadeInTime": -1.0,
      "FadeOutTime": -1.0,
      "Segments": [
        0,
        0,
        1,
        1.328,
        0,
        2.655,
        0,
        3.983,
        0
      ]
    },
    {
      "Target": "Parameter",
      "Id": "Param49",
      "FadeInTime": -1.0,
      "FadeOutTime": -1.0,
      "Segments": [
        0,
        0,
        1,
        1.328,
        0,
        2.655,
        0,
        3.983,
        0
      ]
    },
    {
      "Target": "Parameter",
      "Id": "Param50",
      "FadeInTime": -1.0,
      "FadeOutTime": -1.0,
      "Segments": [
        0,
        0,
        1,
        1.328,
        0,
        2.655,
        0,
        3.983,
        0
      ]
    },
    {
      "Target": "Parameter",
      "Id": "ParamLegFootLZ",
      "FadeInTime": -1.0,
      "FadeOutTime": -1.0,
      "Segments": [
        0,
        28,
        1,
        1.328,
        28,
        2.655,
        28,
        3.983,
        28
      ]
    },
    {
      "Target": "Parameter",
      "Id": "ParamLegFootLX",
      "FadeInTime": -1.0,
      "FadeOutTime": -1.0,
      "Segments": [
        0,
        -30,
        1,
        1.328,
        -30,
        2.655,
        -30,
        3.983,
        -30
      ]
    },
    {
      "Target": "Parameter",
      "Id": "ParamLegFootLY",
      "FadeInTime": -1.0,
      "FadeOutTime": -1.0,
      "Segments": [
        0,
        -13,
        1,
        1.328,
        -13,
        2.655,
        -13,
        3.983,
        -13
      ]
    },
    {
      "Target": "Parameter",
      "Id": "ParamLegLowerRY",
      "FadeInTime": -1.0,
      "FadeOutTime": -1.0,
      "Segments": [
        0,
        -7,
        1,
        1.328,
        -7,
        2.655,
        -7,
        3.983,
        -7
      ]
    },
    {
      "Target": "Parameter",
      "Id": "Param51",
      "FadeInTime": -1.0,
      "FadeOutTime": -1.0,
      "Segments": [
        0,
        0,
        1,
        1.328,
        0,
        2.655,
        0,
        3.983,
        0
      ]
    },
    {
      "Target": "Parameter",
      "Id": "Param55",
      "FadeInTime": -1.0,
      "FadeOutTime": -1.0,
      "Segments": [
        0,
        0,
        1,
        1.328,
        0,
        2.655,
        0,
        3.983,
        0
      ]
    },
    {
      "Target": "Parameter",
      "Id": "Param57",
      "FadeInTime": -1.0,
      "FadeOutTime": -1.0,
      "Segments": [
        0,
        0,
        1,
        1.328,
        0,
        2.655,
        0,
        3.983,
        0
      ]
    },
    {
      "Target": "Parameter",
      "Id": "Param58",
      "FadeInTime": -1.0,
      "FadeOutTime": -1.0,
      "Segments": [
        0,
        0,
        1,
        1.328,
        0,
        2.655,
        0,
        3.983,
        0
      ]
    },
    {
      "Target": "Parameter",
      "Id": "Param56",
      "FadeInTime": -1.0,
      "FadeOutTime": -1.0,
      "Segments": [
        0,
        0,
        1,
        1.328,
        0,
        2.655,
        0,
        3.983,
        0
      ]
    },
    {
      "Target": "Parameter",
      "Id": "Param52",
      "FadeInTime": -1.0,
      "FadeOutTime": -1.0,
      "Segments": [
        0,
        0,
        1,
        1.328,
        0,
        2.655,
        0,
        3.983,
        0
      ]
    },
    {
      "Target": "Parameter",
      "Id": "Param53",
      "FadeInTime": -1.0,
      "FadeOutTime": -1.0,
      "Segments": [
        0,
        0,
        1,
        1.328,
        0,
        2.655,
        0,
        3.983,
        0
      ]
    },
    {
      "Target": "Parameter",
      "Id": "Param54",
      "FadeInTime": -1.0,
      "FadeOutTime": -1.0,
      "Segments": [
        0,
        0,
        1,
        1.328,
        0,
        2.655,
        0,
        3.983,
        0
      ]
    },
    {
      "Target": "Parameter",
      "Id": "Param59",
      "FadeInTime": -1.0,
      "FadeOutTime": -1.0,
      "Segments": [
        0,
        0,
        1,
        1.328,
        0,
        2.655,
        0,
        3.983,
        0
      ]
    },
    {
      "Target": "Parameter",
      "Id": "Param60",
      "FadeInTime": -1.0,
      "FadeOutTime": -1.0,
      "Segments": [
        0,
        0,
        1,
        1.328,
        0,
        2.655,
        0,
        3.983,
        0
      ]
    },
    {
      "Target": "Parameter",
      "Id": "Param61",
      "FadeInTime": -1.0,
      "FadeOutTime": -1.0,
      "Segments": [
        0,
        0,
        1,
        1.328,
        0,
        2.655,
        0,
        3.983,
        0
      ]
    },
    {
      "Target": "Parameter",
      "Id": "Param62",
      "FadeInTime": -1.0,
      "FadeOutTime": -1.0,
      "Segments": [
        0,
        0,
        1,
        1.328,
        0,
        2.655,
        0,
        3.983,
        0
      ]
    },
    {
      "Target": "Parameter",
      "Id": "Param63",
      "FadeInTime": -1.0,
      "FadeOutTime": -1.0,
      "Segments": [
        0,
        0,
        1,
        1.328,
        0,
        2.655,
        0,
        3.983,
        0
      ]
    },
    {
      "Target": "Parameter",
      "Id": "Param64",
      "FadeInTime": -1.0,
      "FadeOutTime": -1.0,
      "Segments": [
        0,
        0,
        1,
        1.328,
        0,
        2.655,
        0,
        3.983,
        0
      ]
    },
    {
      "Target": "Parameter",
      "Id": "Param65",
      "FadeInTime": -1.0,
      "FadeOutTime": -1.0,
      "Segments": [
        0,
        0,
        1,
        1.328,
        0,
        2.655,
        0,
        3.983,
        0
      ]
    },
    {
      "Target": "Parameter",
      "Id": "Param66",
      "FadeInTime": -1.0,
      "FadeOutTime": -1.0,
      "Segments": [
        0,
        0,
        1,
        1.328,
        0,
        2.655,
        0,
        3.983,
        0
      ]
    },
    {
      "Target": "Parameter",
      "Id": "Param67",
      "FadeInTime": -1.0,
      "FadeOutTime": -1.0,
      "Segments": [
        0,
        0,
        1,
        1.328,
        0,
        2.655,
        0,
        3.983,
        0
      ]
    },
    {
      "Target": "Parameter",
      "Id": "Param68",
      "FadeInTime": -1.0,
      "FadeOutTime": -1.0,
      "Segments": [
        0,
        0,
        1,
        1.328,
        0,
        2.655,
        0,
        3.983,
        0
      ]
    },
    {
      "Target": "Parameter",
      "Id": "Param69",
      "FadeInTime": -1.0,
      "FadeOutTime": -1.0,
      "Segments": [
        0,
        0,
        1,
        1.328,
        0,
        2.655,
        0,
        3.983,
        0
      ]
    },
    {
      "Target": "Parameter",
      "Id": "Param70",
      "FadeInTime": -1.0,
      "FadeOutTime": -1.0,
      "Segments": [
        0,
        0,
        1,
        1.328,
        0,
        2.655,
        0,
        3.983,
        0
      ]
    },
    {
      "Target": "Parameter",
      "Id": "Param71",
      "FadeInTime": -1.0,
      "FadeOutTime": -1.0,
      "Segments": [
        0,
        0,
        1,
        1.328,
        0,
        2.655,
        0,
        3.983,
        0
      ]
    },
    {
      "Target": "Parameter",
      "Id": "Param72",
      "FadeInTime": -1.0,
      "FadeOutTime": -1.0,
      "Segments": [
        0,
        0,
        1,
        1.328,
        0,
        2.655,
        0,
        3.983,
        0
      ]
    },
    {
      "Target": "Parameter",
      "Id": "Param73",
      "FadeInTime": -1.0,
      "FadeOutTime": -1.0,
      "Segments": [
        0,
        0,
        1,
        1.328,
        0,
        2.655,
        0,
        3.983,
        0
      ]
    },
    {
      "Target": "Parameter",
      "Id": "Param74",
      "FadeInTime": -1.0,
      "FadeOutTime": -1.0,
      "Segments": [
        0,
        0,
        1,
        1.328,
        0,
        2.655,
        0,
        3.983,
        0
      ]
    },
    {
      "Target": "Parameter",
      "Id": "Param75",
      "FadeInTime": -1.0,
      "FadeOutTime": -1.0,
      "Segments": [
        0,
        0,
        1,
        1.328,
        0,
        2.655,
        0,
        3.983,
        0
      ]
    },
    {
      "Target": "Parameter",
      "Id": "Param76",
      "FadeInTime": -1.0,
      "FadeOutTime": -1.0,
      "Segments": [
        0,
        0,
        1,
        1.328,
        0,
        2.655,
        0,
        3.983,
        0
      ]
    },
    {
      "Target": "Parameter",
      "Id": "Param77",
      "FadeInTime": -1.0,
      "FadeOutTime": -1.0,
      "Segments": [
        0,
        0,
        1,
        1.328,
        0,
        2.655,
        0,
        3.983,
        0
      ]
    },
    {
      "Target": "Parameter",
      "Id": "Param78",
      "FadeInTime": -1.0,
      "FadeOutTime": -1.0,
      "Segments": [
        0,
        0,
        1,
        1.328,
        0,
        2.655,
        0,
        3.983,
        0
      ]
    },
    {
      "Target": "Parameter",
      "Id": "Param79",
      "FadeInTime": -1.0,
      "FadeOutTime": -1.0,
      "Segments": [
        0,
        0,
        1,
        1.328,
        0,
        2.655,
        0,
        3.983,
        0
      ]
    },
    {
      "Target": "Parameter",
      "Id": "Param80",
      "FadeInTime": -1.0,
      "FadeOutTime": -1.0,
      "Segments": [
        0,
        0,
        1,
        1.328,
        0,
        2.655,
        0,
        3.983,
        0
      ]
    },
    {
      "Target": "Parameter",
      "Id": "Param81",
      "FadeInTime": -1.0,
      "FadeOutTime": -1.0,
      "Segments": [
        0,
        0,
        1,
        1.328,
        0,
        2.655,
        0,
        3.983,
        0
      ]
    },
    {
      "Target": "Parameter",
      "Id": "Param82",
      "FadeInTime": -1.0,
      "FadeOutTime": -1.0,
      "Segments": [
        0,
        0,
        1,
        1.328,
        0,
        2.655,
        0,
        3.983,
        0
      ]
    },
    {
      "Target": "Parameter",
      "Id": "Param83",
      "FadeInTime": -1.0,
      "FadeOutTime": -1.0,
      "Segments": [
        0,
        0,
        1,
        1.328,
        0,
        2.655,
        0,
        3.983,
        0
      ]
    },
    {
      "Target": "Parameter",
      "Id": "Param84",
      "FadeInTime": -1.0,
      "FadeOutTime": -1.0,
      "Segments": [
        0,
        0,
        1,
        1.328,
        0,
        2.655,
        0,
        3.983,
        0
      ]
    },
    {
      "Target": "Parameter",
      "Id": "Param85",
      "FadeInTime": -1.0,
      "FadeOutTime": -1.0,
      "Segments": [
        0,
        0,
        1,
        1.328,
        0,
        2.655,
        0,
        3.983,
        0
      ]
    },
    {
      "Target": "Parameter",
      "Id": "Param86",
      "FadeInTime": -1.0,
      "FadeOutTime": -1.0,
      "Segments": [
        0,
        0,
        1,
        1.328,
        0,
        2.655,
        0,
        3.983,
        0
      ]
    },
    {
      "Target": "Parameter",
      "Id": "Param87",
      "FadeInTime": -1.0,
      "FadeOutTime": -1.0,
      "Segments": [
        0,
        0,
        1,
        1.328,
        0,
        2.655,
        0,
        3.983,
        0
      ]
    },
    {
      "Target": "Parameter",
      "Id": "Param88",
      "FadeInTime": -1.0,
      "FadeOutTime": -1.0,
      "Segments": [
        0,
        0,
        1,
        1.328,
        0,
        2.655,
        0,
        3.983,
        0
      ]
    },
    {
      "Target": "Parameter",
      "Id": "Param131",
      "FadeInTime": -1.0,
      "FadeOutTime": -1.0,
      "Segments": [
        0,
        -20.332,
        1,
        1.328,
        -20.332,
        2.655,
        -20.332,
        3.983,
        -20.332
      ]
    },
    {
      "Target": "Parameter",
      "Id": "Param132",
      "FadeInTime": -1.0,
      "FadeOutTime": -1.0,
      "Segments": [
        0,
        -15.304,
        1,
        1.328,
        -15.304,
        2.655,
        -15.304,
        3.983,
        -15.304
      ]
    },
    {
      "Target": "Parameter",
      "Id": "Param133",
      "FadeInTime": -1.0,
      "FadeOutTime": -1.0,
      "Segments": [
        0,
        0,
        1,
        1.328,
        0,
        2.655,
        0,
        3.983,
        0
      ]
    },
    {
      "Target": "Parameter",
      "Id": "Param134",
      "FadeInTime": -1.0,
      "FadeOutTime": -1.0,
      "Segments": [
        0,
        30,
        1,
        1.328,
        30,
        2.655,
        30,
        3.983,
        30
      ]
    },
    {
      "Target": "Parameter",
      "Id": "Param135",
      "FadeInTime": -1.0,
      "FadeOutTime": -1.0,
      "Segments": [
        0,
        0,
        1,
        1.328,
        0,
        2.655,
        0,
        3.983,
        0
      ]
    },
    {
      "Target": "Parameter",
      "Id": "Param136",
      "FadeInTime": -1.0,
      "FadeOutTime": -1.0,
      "Segments": [
        0,
        30,
        1,
        1.328,
        30,
        2.655,
        30,
        3.983,
        30
      ]
    },
    {
      "Target": "Parameter",
      "Id": "Param137",
      "FadeInTime": -1.0,
      "FadeOutTime": -1.0,
      "Segments": [
        0,
        -16.38,
        1,
        1.328,
        -16.38,
        2.655,
        -16.38,
        3.983,
        -16.38
      ]
    },
    {
      "Target": "Parameter",
      "Id": "Param138",
      "FadeInTime": -1.0,
      "FadeOutTime": -1.0,
      "Segments": [
        0,
        -1.98,
        1,
        1.328,
        -1.98,
        2.655,
        -1.98,
        3.983,
        -1.98
      ]
    },
    {
      "Target": "Parameter",
      "Id": "Param139",
      "FadeInTime": -1.0,
      "FadeOutTime": -1.0,
      "Segments": [
        0,
        0,
        1,
        1.328,
        0,
        2.655,
        0,
        3.983,
        0
      ]
    },
    {
      "Target": "Parameter",
      "Id": "Param140",
      "FadeInTime": -1.0,
      "FadeOutTime": -1.0,
      "Segments": [
        0,
        30,
        1,
        1.328,
        30,
        2.655,
        30,
        3.983,
        30
      ]
    },
    {
      "Target": "Parameter",
      "Id": "Param141",
      "FadeInTime": -1.0,
      "FadeOutTime": -1.0,
      "Segments": [
        0,
        0,
        1,
        1.328,
        0,
        2.655,
        0,
        3.983,
        0
      ]
    },
    {
      "Target": "Parameter",
      "Id": "Param142",
      "FadeInTime": -1.0,
      "FadeOutTime": -1.0,
      "Segments": [
        0,
        30,
        1,
        1.328,
        30,
        2.655,
        30,
        3.983,
        30
      ]
    }
  ],
  "UserData": [
    {
      "Time": 0.0,
      "Value": ""
    }
  ]
}