{
  "Version": 3,
  "Meta": {
    "Duration": 1.333,
    "Fps": 60.0,
    "Loop": true,
    "AreBeziersRestricted": true,
    "FadeInTime": 0.0,
    "FadeOutTime": 0.0,
    "CurveCount": 3,
    "TotalSegmentCount": 17,
    "TotalPointCount": 54,
    "UserDataCount": 1,
    "TotalUserDataSize": 0
  },
  "Curves": [
    {
      "Target": "Parameter",
      "Id": "Param32",
      "FadeInTime": -1.0,
      "FadeOutTime": -1.0,
      "Segments": [
        0,
        0,
        1,
        0.056,
        9.638,
        0.111,
        15.74,
        0.167,
        15.74,
        1,
        0.222,
        15.74,
        0.278,
        12.015,
        0.333,
        0,
        1,
        0.378,
        -9.612,
        0.422,
        -17.78,
        0.467,
        -17.78,
        1,
        0.522,
        -17.78,
        0.578,
        -13.203,
        0.633,
        0,
        1,
        0.678,
        10.562,
        0.722,
        18.57,
        0.767,
        18.57,
        1,
        0.845,
        18.57,
        0.922,
        12.429,
        1,
        0,
        1,
        1.056,
        -8.878,
        1.111,
        -13.39,
        1.167,
        -13.39,
        1,
        1.222,
        -13.39,
        1.278,
        -9.638,
        1.333,
        0
      ]
    },
    {
      "Target": "Parameter",
      "Id": "Param33",
      "FadeInTime": -1.0,
      "FadeOutTime": -1.0,
      "Segments": [
        0,
        -5.39,
        1,
        0.056,
        -5.39,
        0.111,
        -4.376,
        0.167,
        0,
        1,
        0.222,
        4.376,
        0.278,
        8.57,
        0.333,
        8.57,
        1,
        0.378,
        8.57,
        0.422,
        5.84,
        0.467,
        0,
        1,
        0.522,
        -7.3,
        0.578,
        -11.15,
        0.633,
        -11.15,
        1,
        0.678,
        -11.15,
        0.722,
        -4.858,
        0.767,
        0,
        1,
        0.845,
        8.502,
        0.922,
        10.8,
        1,
        10.8,
        1,
        1.056,
        10.8,
        1.111,
        4.71,
        1.167,
        0,
        1,
        1.222,
        -4.71,
        1.278,
        -5.39,
        1.333,
        -5.39
      ]
    },
    {
      "Target": "Parameter",
      "Id": "Param31",
      "FadeInTime": -1.0,
      "FadeOutTime": -1.0,
      "Segments": [
        0,
        1,
        1,
        0.444,
        1,
        0.889,
        1,
        1.333,
        1
      ]
    }
  ],
  "UserData": [
    {
      "Time": 0.0,
      "Value": ""
    }
  ]
}